{"6601":{"saturday":{"785265":{"startSamples":[494,480],"endSamples":[501,482],"avgStart":"08:07","avgEnd":"08:12","samples":2},"785266":{"startSamples":[600,610],"endSamples":[607,981],"avgStart":"10:05","samples":2,"avgEnd":"13:14"},"785267":{"startSamples":[718],"endSamples":[721],"avgStart":"11:58","samples":1,"avgEnd":"12:01"},"785268":{"startSamples":[840],"endSamples":[842],"avgStart":"14:00","samples":1,"avgEnd":"14:02"},"785269":{"startSamples":[963],"endSamples":[1043],"avgStart":"16:03","samples":1,"avgEnd":"17:23"},"785270":{"startSamples":[547],"endSamples":[549],"avgStart":"09:07","samples":1,"avgEnd":"09:09"},"785271":{"startSamples":[667],"endSamples":[861],"avgStart":"11:07","samples":1,"avgEnd":"14:21"},"785274":{"startSamples":[1030],"endSamples":[1036],"avgStart":"17:10","samples":1,"avgEnd":"17:16"}},"weekday":{"983730":{"startSamples":[450,437,463],"endSamples":[588,444,626],"avgStart":"07:30","samples":3,"avgEnd":"09:13"},"983733":{"startSamples":[557],"endSamples":[557],"avgStart":"09:17","samples":1,"avgEnd":"09:17"},"983743":{"startSamples":[512,496],"endSamples":[522,506],"avgStart":"08:24","samples":2,"avgEnd":"08:34"}}},"6602":{"weekday":{"983731":{"startSamples":[512,496],"endSamples":[522,506],"avgStart":"08:24","samples":2,"avgEnd":"08:34"},"983742":{"startSamples":[450,437],"endSamples":[455,444],"avgStart":"07:24","avgEnd":"07:30","samples":2},"983753":{"startSamples":[547],"endSamples":[557],"avgStart":"09:07","samples":1,"avgEnd":"09:17"}},"saturday":{"785260":{"startSamples":[603],"endSamples":[1090],"avgStart":"10:03","samples":1,"avgEnd":"18:10"}}},"6603":{"weekday":{"983732":{"startSamples":[578,547],"endSamples":[984],"avgStart":"09:23","samples":2,"avgEnd":"16:24"},"983734":{"startSamples":[664,662],"endSamples":[674,972],"avgStart":"11:03","samples":2,"avgEnd":"13:43"},"983735":{"startSamples":[768,768],"endSamples":[1016,772],"avgStart":"12:48","samples":2,"avgEnd":"14:54"},"983737":{"startSamples":[875],"endSamples":[876],"avgStart":"14:35","samples":1,"avgEnd":"14:36"},"983741":{"startSamples":[980,980],"endSamples":[986,984],"avgStart":"16:20","samples":2,"avgEnd":"16:25"},"983744":{"startSamples":[616],"endSamples":[619],"avgStart":"10:16","avgEnd":"10:19","samples":1},"983746":{"startSamples":[723],"endSamples":[977],"avgStart":"12:03","samples":1,"avgEnd":"16:17"}}},"6604":{"weekday":{"983736":{"startSamples":[857,852,847,828],"endSamples":[1068,1133,1134,988],"avgStart":"14:06","samples":4,"avgEnd":"18:01"},"983748":{"startSamples":[874,878],"endSamples":[1146,1162],"avgStart":"14:36","samples":2,"avgEnd":"19:14"},"983751":{"startSamples":[1077],"endSamples":[1138],"avgStart":"17:57","samples":1,"avgEnd":"18:58"},"983752":{"startSamples":[1137],"endSamples":[1140],"avgStart":"18:57","samples":1,"avgEnd":"19:00"}}}}