{"7501":{"weekday":{"791509":{"startSamples":[618,621,627],"endSamples":[771,707,794],"avgStart":"10:22","samples":3,"avgEnd":"12:37"},"791514":{"startSamples":[546],"endSamples":[688],"avgStart":"09:06","samples":1,"avgEnd":"11:28"},"791526":{"startSamples":[422,415,419,432],"endSamples":[431,557,498,436],"avgStart":"07:02","samples":4,"avgEnd":"08:01"},"791530":{"startSamples":[356],"endSamples":[498],"avgStart":"05:56","samples":1,"avgEnd":"08:18"},"791533":{"startSamples":[291,287,295],"endSamples":[733,733,466],"avgStart":"04:51","samples":3,"avgEnd":"10:44"},"791584":{"startSamples":[315,323,331],"endSamples":[324,331,331],"avgStart":"05:23","samples":3,"avgEnd":"05:29"},"791586":{"startSamples":[512],"endSamples":[760],"avgStart":"08:32","samples":1,"avgEnd":"12:40"},"791592":{"startSamples":[442,442],"endSamples":[674,527],"avgStart":"07:22","samples":2,"avgEnd":"10:01"},"791635":{"startSamples":[769,770],"endSamples":[776,776],"avgStart":"12:50","samples":2,"avgEnd":"12:56"},"791638":{"startSamples":[713,713],"endSamples":[718,780],"avgStart":"11:53","samples":2,"avgEnd":"12:29"},"791640":{"startSamples":[662],"endSamples":[794],"avgStart":"11:02","samples":1,"avgEnd":"13:14"}},"saturday":{"791652":{"startSamples":[311],"endSamples":[318],"avgStart":"05:11","avgEnd":"05:18","samples":1},"791692":{"startSamples":[603],"endSamples":[733],"avgStart":"10:03","samples":1,"avgEnd":"12:13"},"791699":{"startSamples":[394],"endSamples":[403],"avgStart":"06:34","samples":1,"avgEnd":"06:43"},"791770":{"startSamples":[316],"endSamples":[325],"avgStart":"05:16","samples":1,"avgEnd":"05:25"},"791810":{"startSamples":[339],"endSamples":[339],"avgStart":"05:39","avgEnd":"05:39","samples":1}}},"7502":{"weekday":{"791512":{"startSamples":[578],"endSamples":[588],"avgStart":"09:38","samples":1,"avgEnd":"09:48"},"791518":{"startSamples":[512,512,499,499],"endSamples":[522,522,506,623],"avgStart":"08:26","samples":4,"avgEnd":"09:03"},"791524":{"startSamples":[450,433],"endSamples":[453,528],"avgStart":"07:22","avgEnd":"08:11","samples":2},"791532":{"startSamples":[317,323,331],"endSamples":[444,492,337],"avgStart":"05:24","samples":3,"avgEnd":"07:04"},"791579":{"startSamples":[542,532],"endSamples":[551,532],"avgStart":"08:57","samples":2,"avgEnd":"09:02"},"791582":{"startSamples":[408],"endSamples":[551],"avgStart":"06:48","samples":1,"avgEnd":"09:11"},"791583":{"startSamples":[353],"endSamples":[359],"avgStart":"05:53","avgEnd":"05:59","samples":1},"791590":{"startSamples":[463],"endSamples":[624],"avgStart":"07:43","samples":1,"avgEnd":"10:24"}},"saturday":{"791689":{"startSamples":[673],"endSamples":[675],"avgStart":"11:13","samples":1,"avgEnd":"11:15"},"791691":{"startSamples":[613],"endSamples":[613],"avgStart":"10:13","samples":1,"avgEnd":"10:13"},"791709":{"startSamples":[788],"endSamples":[981],"avgStart":"13:08","samples":1,"avgEnd":"16:21"},"791723":{"startSamples":[454],"endSamples":[603],"avgStart":"07:34","samples":1,"avgEnd":"10:03"},"791771":{"startSamples":[347],"endSamples":[432],"avgStart":"05:47","samples":1,"avgEnd":"07:12"},"791772":{"startSamples":[403],"endSamples":[412],"avgStart":"06:43","samples":1,"avgEnd":"06:52"},"791774":{"startSamples":[470],"endSamples":[523],"avgStart":"07:50","samples":1,"avgEnd":"08:43"},"791778":{"startSamples":[641,619],"endSamples":[842,620],"avgStart":"10:30","samples":2,"avgEnd":"12:11"},"791780":{"startSamples":[681],"endSamples":[734],"avgStart":"11:21","samples":1,"avgEnd":"12:14"},"791782":{"startSamples":[741,741],"endSamples":[808,807],"avgStart":"12:21","samples":2,"avgEnd":"13:28"},"791786":{"startSamples":[860],"endSamples":[864],"avgStart":"14:20","samples":1,"avgEnd":"14:24"},"791809":{"startSamples":[389],"endSamples":[482],"avgStart":"06:29","samples":1,"avgEnd":"08:02"},"791813":{"startSamples":[494],"endSamples":[504],"avgStart":"08:14","samples":1,"avgEnd":"08:24"},"791817":{"startSamples":[661],"endSamples":[668],"avgStart":"11:01","avgEnd":"11:08","samples":1},"791823":{"startSamples":[852],"endSamples":[859],"avgStart":"14:12","samples":1,"avgEnd":"14:19"}}},"7503":{"weekday":{"791515":{"startSamples":[542],"endSamples":[552],"avgStart":"09:02","samples":1,"avgEnd":"09:12"},"791521":{"startSamples":[463],"endSamples":[626],"avgStart":"07:43","samples":1,"avgEnd":"10:26"},"791527":{"startSamples":[422,408,419],"endSamples":[428,557,429],"avgStart":"06:56","avgEnd":"07:51","samples":3},"791531":{"startSamples":[353,337],"endSamples":[357,442],"avgStart":"05:45","avgEnd":"06:40","samples":2},"791587":{"startSamples":[512,512,496,496],"endSamples":[519,516,506,623],"avgStart":"08:24","avgEnd":"09:01","samples":4},"791593":{"startSamples":[450,437],"endSamples":[450,444],"avgStart":"07:24","avgEnd":"07:27","samples":2},"791641":{"startSamples":[633],"endSamples":[636],"avgStart":"10:33","samples":1,"avgEnd":"10:36"},"791647":{"startSamples":[578],"endSamples":[587],"avgStart":"09:38","samples":1,"avgEnd":"09:47"}},"saturday":{"791672":{"startSamples":[1026],"endSamples":[1036],"avgStart":"17:06","samples":1,"avgEnd":"17:16"},"791702":{"startSamples":[922],"endSamples":[976],"avgStart":"15:22","samples":1,"avgEnd":"16:16"},"791718":{"startSamples":[603],"endSamples":[851],"avgStart":"10:03","samples":1,"avgEnd":"14:11"},"791749":{"startSamples":[977],"endSamples":[980],"avgStart":"16:17","samples":1,"avgEnd":"16:20"},"791773":{"startSamples":[430],"endSamples":[439],"avgStart":"07:10","samples":1,"avgEnd":"07:19"},"791777":{"startSamples":[598],"endSamples":[808],"avgStart":"09:58","samples":1,"avgEnd":"13:28"},"791779":{"startSamples":[650],"endSamples":[973],"avgStart":"10:50","samples":1,"avgEnd":"16:13"},"791812":{"startSamples":[473,464],"endSamples":[476,733],"avgStart":"07:49","avgEnd":"10:05","samples":2},"791814":{"startSamples":[539],"endSamples":[549],"avgStart":"08:59","samples":1,"avgEnd":"09:09"},"791820":{"startSamples":[737],"endSamples":[973],"avgStart":"12:17","samples":1,"avgEnd":"16:13"},"791824":{"startSamples":[857],"endSamples":[942],"avgStart":"14:17","samples":1,"avgEnd":"15:42"}}},"7504":{"weekday":{"791516":{"startSamples":[552,523],"endSamples":[557,532],"avgStart":"08:58","samples":2,"avgEnd":"09:05"},"791522":{"startSamples":[453,463],"endSamples":[460,472],"avgStart":"07:38","samples":2,"avgEnd":"07:46"},"791528":{"startSamples":[408,416],"endSamples":[412,417],"avgStart":"06:52","avgEnd":"06:55","samples":2},"791580":{"startSamples":[422,437,419,432],"endSamples":[545,674,500,437],"avgStart":"07:08","samples":4,"avgEnd":"08:59"},"791588":{"startSamples":[496],"endSamples":[505],"avgStart":"08:16","samples":1,"avgEnd":"08:25"}},"saturday":{"791683":{"startSamples":[793],"endSamples":[843],"avgStart":"13:13","samples":1,"avgEnd":"14:03"},"791686":{"startSamples":[733],"endSamples":[733],"avgStart":"12:13","samples":1,"avgEnd":"12:13"},"791750":{"startSamples":[992,980],"endSamples":[1184,1032],"avgStart":"16:26","samples":2,"avgEnd":"18:28"},"791752":{"startSamples":[1040],"endSamples":[1043],"avgStart":"17:20","samples":1,"avgEnd":"17:23"},"791755":{"startSamples":[1101],"endSamples":[1102],"avgStart":"18:21","samples":1,"avgEnd":"18:22"},"791757":{"startSamples":[1161],"endSamples":[1168],"avgStart":"19:21","samples":1,"avgEnd":"19:28"},"791759":{"startSamples":[1225],"endSamples":[1227],"avgStart":"20:25","samples":1,"avgEnd":"20:27"},"791761":{"startSamples":[1289],"endSamples":[1289],"avgStart":"21:29","samples":1,"avgEnd":"21:29"},"791787":{"startSamples":[937,920],"endSamples":[943,930],"avgStart":"15:29","avgEnd":"15:37","samples":2},"791788":{"startSamples":[893],"endSamples":[968],"avgStart":"14:53","samples":1,"avgEnd":"16:08"},"791794":{"startSamples":[1082],"endSamples":[1203],"avgStart":"18:02","samples":1,"avgEnd":"20:03"}}},"7505":{"weekday":{"791505":{"startSamples":[708,704,719],"endSamples":[912,904,869],"avgStart":"11:50","samples":3,"avgEnd":"14:55"},"791519":{"startSamples":[512,512,496],"endSamples":[516,733,663],"avgStart":"08:27","avgEnd":"10:37","samples":3},"791525":{"startSamples":[425,437,425,432],"endSamples":[431,854,500,532],"avgStart":"07:10","samples":4,"avgEnd":"09:39"},"791557":{"startSamples":[888],"endSamples":[888],"avgStart":"14:48","samples":1,"avgEnd":"14:48"},"791574":{"startSamples":[760,762,788],"endSamples":[760,876,882],"avgStart":"12:50","samples":3,"avgEnd":"13:59"},"791585":{"startSamples":[520],"endSamples":[756],"avgStart":"08:40","samples":1,"avgEnd":"12:36"},"791591":{"startSamples":[452,463],"endSamples":[730,623],"avgStart":"07:38","samples":2,"avgEnd":"11:17"},"791629":{"startSamples":[860,860],"endSamples":[866,867],"avgStart":"14:20","samples":2,"avgEnd":"14:27"},"791637":{"startSamples":[733],"endSamples":[862],"avgStart":"12:13","samples":1,"avgEnd":"14:22"},"791643":{"startSamples":[679,672],"endSamples":[852,672],"avgStart":"11:16","samples":2,"avgEnd":"12:42"}},"saturday":{"791665":{"startSamples":[1194],"endSamples":[1202],"avgStart":"19:54","avgEnd":"20:02","samples":1},"791671":{"startSamples":[1033],"endSamples":[1082],"avgStart":"17:13","samples":1,"avgEnd":"18:02"},"791677":{"startSamples":[919],"endSamples":[1029],"avgStart":"15:19","samples":1,"avgEnd":"17:09"},"791735":{"startSamples":[1275],"endSamples":[1285],"avgStart":"21:15","samples":1,"avgEnd":"21:25"},"791740":{"startSamples":[1140],"endSamples":[1146],"avgStart":"19:00","avgEnd":"19:06","samples":1},"791756":{"startSamples":[1139],"endSamples":[1280],"avgStart":"18:59","samples":1,"avgEnd":"21:20"},"791795":{"startSamples":[1112,1097],"endSamples":[1117,51],"avgStart":"18:25","avgEnd":"09:44","samples":2},"791797":{"startSamples":[1175],"endSamples":[1178],"avgStart":"19:35","avgEnd":"19:38","samples":1},"791801":{"startSamples":[1286,1286],"endSamples":[80,53],"avgStart":"21:26","samples":2,"avgEnd":"01:07"}}},"7506":{"weekday":{"791507":{"startSamples":[660,662],"endSamples":[665,672],"avgStart":"11:01","samples":2,"avgEnd":"11:09"},"791511":{"startSamples":[586],"endSamples":[588],"avgStart":"09:46","samples":1,"avgEnd":"09:48"},"791517":{"startSamples":[512,512,522],"endSamples":[522,522,636],"avgStart":"08:35","samples":3,"avgEnd":"09:20"},"791523":{"startSamples":[450,443,463],"endSamples":[460,674,465],"avgStart":"07:32","samples":3,"avgEnd":"08:53"},"791589":{"startSamples":[472,490],"endSamples":[626,492],"avgStart":"08:01","samples":2,"avgEnd":"09:19"},"791642":{"startSamples":[618],"endSamples":[714],"avgStart":"10:18","samples":1,"avgEnd":"11:54"},"791649":{"startSamples":[544,547],"endSamples":[682,713],"avgStart":"09:06","samples":2,"avgEnd":"11:38"}},"saturday":{"791662":{"startSamples":[1275],"endSamples":[49],"avgStart":"21:15","samples":1,"avgEnd":"00:49"},"791666":{"startSamples":[1146],"endSamples":[1198],"avgStart":"19:06","samples":1,"avgEnd":"19:58"},"791669":{"startSamples":[1080],"endSamples":[1090],"avgStart":"18:00","samples":1,"avgEnd":"18:10"}}},"7507":{"weekday":{"791504":{"startSamples":[723,727,720],"endSamples":[1077,978,1008],"avgStart":"12:03","samples":3,"avgEnd":"17:01"},"791538":{"startSamples":[1208],"endSamples":[1211],"avgStart":"20:08","samples":1,"avgEnd":"20:11"},"791541":{"startSamples":[1173],"endSamples":[1183],"avgStart":"19:33","samples":1,"avgEnd":"19:43"},"791545":{"startSamples":[1067,1064,1058],"endSamples":[1070,1074,1119],"avgStart":"17:43","samples":3,"avgEnd":"18:08"},"791550":{"startSamples":[1003,990],"endSamples":[1075,1050],"avgStart":"16:37","samples":2,"avgEnd":"17:43"},"791560":{"startSamples":[851,852],"endSamples":[948,952],"avgStart":"14:12","samples":2,"avgEnd":"15:50"},"791572":{"startSamples":[792],"endSamples":[878],"avgStart":"13:12","samples":1,"avgEnd":"14:38"},"791607":{"startSamples":[1191,1182,1187,1177,1196,1203],"endSamples":[1197,1192,1197,1187,1200,1206],"avgStart":"19:49","avgEnd":"19:57","samples":6},"791611":{"startSamples":[1139,1097],"endSamples":[1197,1216],"avgStart":"18:38","samples":2,"avgEnd":"20:07"},"791621":{"startSamples":[955,955],"endSamples":[1080,1080],"avgStart":"15:55","samples":2,"avgEnd":"18:00"},"791627":{"startSamples":[884],"endSamples":[1219],"avgStart":"14:44","samples":1,"avgEnd":"20:19"},"791632":{"startSamples":[842,824],"endSamples":[845,909],"avgStart":"13:53","avgEnd":"14:37","samples":2},"791636":{"startSamples":[753,766,766,762,770],"endSamples":[866,772,776,976,1158],"avgStart":"12:43","samples":5,"avgEnd":"15:10"}}},"7508":{"weekday":{"791552":{"startSamples":[960,976],"endSamples":[1013,986],"avgStart":"16:08","samples":2,"avgEnd":"16:40"},"791556":{"startSamples":[898],"endSamples":[971],"avgStart":"14:58","samples":1,"avgEnd":"16:11"},"791561":{"startSamples":[856,842,857,852,847,840,859],"endSamples":[864,1013,864,984,952,843,864],"avgStart":"14:10","avgEnd":"15:12","samples":7},"791573":{"startSamples":[784,778,794],"endSamples":[973,837,800],"avgStart":"13:05","samples":3,"avgEnd":"14:30"},"791618":{"startSamples":[1008],"endSamples":[1012],"avgStart":"16:48","avgEnd":"16:52","samples":1},"791623":{"startSamples":[939],"endSamples":[1008],"avgStart":"15:39","samples":1,"avgEnd":"16:48"},"791628":{"startSamples":[872],"endSamples":[984],"avgStart":"14:32","samples":1,"avgEnd":"16:24"},"791633":{"startSamples":[823],"endSamples":[991],"avgStart":"13:43","samples":1,"avgEnd":"16:31"}}},"7509":{"weekday":{"791559":{"startSamples":[864,866,878,864],"endSamples":[866,876,888,869],"avgStart":"14:28","samples":4,"avgEnd":"14:35"},"791571":{"startSamples":[823,834,804],"endSamples":[914,904,804],"avgStart":"13:40","samples":3,"avgEnd":"14:34"},"791631":{"startSamples":[856,842,857,852,847],"endSamples":[858,852,867,857,857],"avgStart":"14:11","avgEnd":"14:18","samples":5}}},"7510":{"weekday":{"791549":{"startSamples":[1007,1005],"endSamples":[1017,1057],"avgStart":"16:46","samples":2,"avgEnd":"17:17"},"791558":{"startSamples":[878],"endSamples":[964],"avgStart":"14:38","samples":1,"avgEnd":"16:04"},"791563":{"startSamples":[823,834],"endSamples":[833,900],"avgStart":"13:49","samples":2,"avgEnd":"14:27"},"791615":{"startSamples":[1045,1036],"endSamples":[1055,1039],"avgStart":"17:21","samples":2,"avgEnd":"17:27"},"791620":{"startSamples":[967,967],"endSamples":[1044,1029],"avgStart":"16:07","samples":2,"avgEnd":"17:17"},"791625":{"startSamples":[908],"endSamples":[988],"avgStart":"15:08","samples":1,"avgEnd":"16:28"},"791630":{"startSamples":[856,848,857,852,848,866,859],"endSamples":[960,1013,986,984,1018,1071,949],"avgStart":"14:15","samples":7,"avgEnd":"16:37"}}},"7511":{"weekday":{"791540":{"startSamples":[1182],"endSamples":[1190],"avgStart":"19:42","avgEnd":"19:50","samples":1},"791543":{"startSamples":[1113],"endSamples":[1266],"avgStart":"18:33","samples":1,"avgEnd":"21:06"},"791547":{"startSamples":[1035,1035],"endSamples":[1044,1039],"avgStart":"17:15","samples":2,"avgEnd":"17:22"},"791551":{"startSamples":[976,975,975],"endSamples":[1130,984,1324],"avgStart":"16:15","samples":3,"avgEnd":"19:06"},"791555":{"startSamples":[911],"endSamples":[1055],"avgStart":"15:11","samples":1,"avgEnd":"17:35"},"791568":{"startSamples":[1424],"endSamples":[1426],"avgStart":"23:44","samples":1,"avgEnd":"23:46"},"791600":{"startSamples":[1332],"endSamples":[1333],"avgStart":"22:12","samples":1,"avgEnd":"22:13"},"791602":{"startSamples":[1277,1271,1271],"endSamples":[1287,1276],"avgStart":"21:13","samples":3,"avgEnd":"21:22"},"791606":{"startSamples":[1196,1196,1209,1207,1202],"endSamples":[1293,1291,1216,1410,1410],"avgStart":"20:02","samples":5,"avgEnd":"22:04"},"791609":{"startSamples":[1136,1136,1136,1152,1153,1148],"endSamples":[1142,1190,1318,1160,1155,1156],"avgStart":"19:04","samples":6,"avgEnd":"19:47"},"791613":{"startSamples":[1066],"endSamples":[1187],"avgStart":"17:46","samples":1,"avgEnd":"19:47"},"791617":{"startSamples":[1006,1006],"endSamples":[1129,1059],"avgStart":"16:46","samples":2,"avgEnd":"18:14"},"791622":{"startSamples":[953,944,950,963,962,944],"endSamples":[1132,952,1080,967,964,1002],"avgStart":"15:53","samples":6,"avgEnd":"16:56"}}},"7512":{"weekday":{"791548":{"startSamples":[1049],"endSamples":[1105],"avgStart":"17:29","samples":1,"avgEnd":"18:25"},"791553":{"startSamples":[953,947,974,950,963,962,947],"endSamples":[963,952,974,959,1105,1099,1000],"avgStart":"15:57","samples":7,"avgEnd":"16:47"},"791610":{"startSamples":[1132,1122,1128,1131],"endSamples":[1137,1132,1137,1140],"avgStart":"18:48","avgEnd":"18:57","samples":4},"791614":{"startSamples":[1070,1065,1070,1053],"endSamples":[1072,1072,1077,1123],"avgStart":"17:45","avgEnd":"18:06","samples":4},"791619":{"startSamples":[979,979,979,981],"endSamples":[1075,1133,1137,991],"avgStart":"16:20","samples":4,"avgEnd":"18:04"},"791624":{"startSamples":[939],"endSamples":[943],"avgStart":"15:39","avgEnd":"15:43","samples":1}}},"7513":{"weekday":{"791536":{"startSamples":[1268,1268],"endSamples":[172],"avgStart":"21:08","samples":2,"avgEnd":"02:52"},"791539":{"startSamples":[1188],"endSamples":[1287],"avgStart":"19:48","samples":1,"avgEnd":"21:27"},"791542":{"startSamples":[1132,1127,1128,1126],"endSamples":[74,1132,1290,1177],"avgStart":"18:48","samples":4,"avgEnd":"15:18"},"791546":{"startSamples":[1070,1065,1067,1061,1070,1064,1050,1053],"endSamples":[1074,1073,1074,1070,118,1326,1212,1063],"avgStart":"17:43","avgEnd":"16:41","samples":8},"791565":{"startSamples":[118],"endSamples":[128],"avgStart":"01:58","samples":1,"avgEnd":"02:08"},"791566":{"startSamples":[60,71],"endSamples":[63,81],"avgStart":"01:06","samples":2,"avgEnd":"01:12"},"791569":{"startSamples":[1418],"endSamples":[1418],"avgStart":"23:38","avgEnd":"23:38","samples":1},"791594":{"startSamples":[132],"endSamples":[142],"avgStart":"02:12","samples":1,"avgEnd":"02:22"},"791595":{"startSamples":[103],"endSamples":[113],"avgStart":"01:43","samples":1,"avgEnd":"01:53"},"791605":{"startSamples":[1216,1216],"endSamples":[1219,1413],"avgStart":"20:16","samples":2,"avgEnd":"21:56"},"791608":{"startSamples":[1156,1156,1173],"endSamples":[1210,113,1176],"avgStart":"19:22","samples":3,"avgEnd":"13:53"},"791612":{"startSamples":[1095,1089],"endSamples":[1103,1152],"avgStart":"18:12","samples":2,"avgEnd":"18:48"}}},"7602":{"saturday":{"791791":{"startSamples":[992,976],"endSamples":[996,1033],"avgStart":"16:24","avgEnd":"16:55","samples":2},"791793":{"startSamples":[1051,1036,1036],"endSamples":[1061,1093,1092],"avgStart":"17:21","samples":3,"avgEnd":"18:02"}}},"7604":{"saturday":{"791745":{"startSamples":[1026],"endSamples":[1090],"avgStart":"17:06","samples":1,"avgEnd":"18:10"}}}}