{"6121":{"weekday":{"785905":{"startSamples":[660],"endSamples":[665],"avgStart":"11:00","samples":1,"avgEnd":"11:05"},"785911":{"startSamples":[512],"endSamples":[513],"avgStart":"08:32","avgEnd":"08:33","samples":1},"785931":{"startSamples":[755],"endSamples":[1015],"avgStart":"12:35","samples":1,"avgEnd":"16:55"},"785958":{"startSamples":[522],"endSamples":[522],"avgStart":"08:42","samples":1,"avgEnd":"08:42"}}},"6122":{"weekday":{"785950":{"startSamples":[760],"endSamples":[866],"avgStart":"12:40","samples":1,"avgEnd":"14:26"},"785959":{"startSamples":[512],"endSamples":[751],"avgStart":"08:32","samples":1,"avgEnd":"12:31"}}},"6123":{"weekday":{"785910":{"startSamples":[515],"endSamples":[861],"avgStart":"08:35","samples":1,"avgEnd":"14:21"},"785924":{"startSamples":[960],"endSamples":[],"avgStart":"16:00","samples":1}}},"6124":{"weekday":{"785935":{"startSamples":[953],"endSamples":[],"avgStart":"15:53","samples":1}}}}