{"4001":{"weekday":{"814958":{"startSamples":[258],"endSamples":[268],"avgStart":"04:18","samples":1,"avgEnd":"04:28"}},"saturday":{"815242":{"startSamples":[855],"endSamples":[],"avgStart":"14:15","samples":1},"815254":{"startSamples":[605],"endSamples":[800],"avgStart":"10:05","samples":1,"avgEnd":"13:20"},"815262":{"startSamples":[429],"endSamples":[504],"avgStart":"07:09","samples":1,"avgEnd":"08:24"},"815280":{"startSamples":[339],"endSamples":[345],"avgStart":"05:39","avgEnd":"05:45","samples":1}}},"4002":{"weekday":{"814928":{"startSamples":[265],"endSamples":[268],"avgStart":"04:25","samples":1,"avgEnd":"04:28"}},"saturday":{"815240":{"startSamples":[799],"endSamples":[859],"avgStart":"13:19","samples":1,"avgEnd":"14:19"},"815248":{"startSamples":[339],"endSamples":[498],"avgStart":"05:39","samples":1,"avgEnd":"08:18"},"815255":{"startSamples":[665],"endSamples":[738],"avgStart":"11:05","samples":1,"avgEnd":"12:18"},"815286":{"startSamples":[598],"endSamples":[607],"avgStart":"09:58","samples":1,"avgEnd":"10:07"}}},"4003":{"saturday":{"815257":{"startSamples":[661],"endSamples":[661],"avgStart":"11:01","avgEnd":"11:01","samples":1},"815277":{"startSamples":[429],"endSamples":[439],"avgStart":"07:09","samples":1,"avgEnd":"07:19"},"815289":{"startSamples":[668],"endSamples":[671],"avgStart":"11:08","samples":1,"avgEnd":"11:11"},"815293":{"startSamples":[799],"endSamples":[808],"avgStart":"13:19","samples":1,"avgEnd":"13:28"}}},"4004":{"saturday":{"815241":{"startSamples":[799],"endSamples":[808],"avgStart":"13:19","samples":1,"avgEnd":"13:28"},"815256":{"startSamples":[665],"endSamples":[671],"avgStart":"11:05","samples":1,"avgEnd":"11:11"},"815284":{"startSamples":[503],"endSamples":[601],"avgStart":"08:23","samples":1,"avgEnd":"10:01"},"815295":{"startSamples":[863],"endSamples":[],"avgStart":"14:23","samples":1}}},"4005":{"weekday":{"814969":{"startSamples":[430],"endSamples":[547],"avgStart":"07:10","samples":1,"avgEnd":"09:07"},"814987":{"startSamples":[512],"endSamples":[522],"avgStart":"08:32","samples":1,"avgEnd":"08:42"}}},"4007":{"weekday":{"814988":{"startSamples":[518,542],"endSamples":[760,776],"avgStart":"08:50","samples":2,"avgEnd":"12:48"}}},"4008":{"weekday":{"814943":{"startSamples":[542],"endSamples":[688],"avgStart":"09:02","samples":1,"avgEnd":"11:28"},"814947":{"startSamples":[655],"endSamples":[665],"avgStart":"10:55","samples":1,"avgEnd":"11:05"},"815054":{"startSamples":[422],"endSamples":[422],"avgStart":"07:02","avgEnd":"07:02","samples":1}}},"4010":{"weekday":{"815061":{"startSamples":[512],"endSamples":[522],"avgStart":"08:32","samples":1,"avgEnd":"08:42"},"815068":{"startSamples":[422],"endSamples":[431],"avgStart":"07:02","samples":1,"avgEnd":"07:11"}}},"4012":{"weekday":{"815056":{"startSamples":[422],"endSamples":[431],"avgStart":"07:02","samples":1,"avgEnd":"07:11"},"815062":{"startSamples":[512],"endSamples":[522],"avgStart":"08:32","samples":1,"avgEnd":"08:42"}}},"4013":{"weekday":{"814979":{"startSamples":[422],"endSamples":[427],"avgStart":"07:02","avgEnd":"07:07","samples":1},"814985":{"startSamples":[512],"endSamples":[519],"avgStart":"08:32","avgEnd":"08:39","samples":1},"815042":{"startSamples":[766],"endSamples":[776],"avgStart":"12:46","samples":1,"avgEnd":"12:56"},"815046":{"startSamples":[655],"endSamples":[760],"avgStart":"10:55","samples":1,"avgEnd":"12:40"}}},"4014":{"weekday":{"815045":{"startSamples":[655],"endSamples":[759],"avgStart":"10:55","samples":1,"avgEnd":"12:39"},"815076":{"startSamples":[542],"endSamples":[686],"avgStart":"09:02","samples":1,"avgEnd":"11:26"}}},"4015":{"weekday":{"814968":{"startSamples":[422],"endSamples":[431],"avgStart":"07:02","samples":1,"avgEnd":"07:11"},"814974":{"startSamples":[512],"endSamples":[522],"avgStart":"08:32","samples":1,"avgEnd":"08:42"}}},"4016":{"weekday":{"815077":{"startSamples":[542],"endSamples":[552],"avgStart":"09:02","samples":1,"avgEnd":"09:12"}}},"4017":{"weekday":{"814994":{"startSamples":[1007,1003],"endSamples":[1013,1075],"avgStart":"16:45","avgEnd":"17:24","samples":2},"815000":{"startSamples":[1070],"endSamples":[1080],"avgStart":"17:50","samples":1,"avgEnd":"18:00"}}},"4018":{"weekday":{"815051":{"startSamples":[856,842],"endSamples":[960,952],"avgStart":"14:09","samples":2,"avgEnd":"15:56"},"815092":{"startSamples":[1132,1122],"endSamples":[1142,1132],"avgStart":"18:47","samples":2,"avgEnd":"18:57"}}},"4019":{"weekday":{"814952":{"startSamples":[842],"endSamples":[847],"avgStart":"14:02","avgEnd":"14:07","samples":1},"815003":{"startSamples":[953,942],"endSamples":[955,952],"avgStart":"15:48","avgEnd":"15:54","samples":2},"815009":{"startSamples":[1015],"endSamples":[1017],"avgStart":"16:55","samples":1,"avgEnd":"16:57"}}},"4020":{"weekday":{"815082":{"startSamples":[960],"endSamples":[963],"avgStart":"16:00","samples":1,"avgEnd":"16:03"},"815088":{"startSamples":[1070,1065],"endSamples":[1079,1075],"avgStart":"17:48","samples":2,"avgEnd":"17:57"},"815110":{"startSamples":[856],"endSamples":[866],"avgStart":"14:16","samples":1,"avgEnd":"14:26"}}},"4021":{"weekday":{"814942":{"startSamples":[856,850],"endSamples":[866,852],"avgStart":"14:13","samples":2,"avgEnd":"14:19"},"814992":{"startSamples":[955],"endSamples":[963],"avgStart":"15:55","samples":1,"avgEnd":"16:03"},"815011":{"startSamples":[1070,1065,1073],"endSamples":[1073,1070,1073],"avgStart":"17:49","avgEnd":"17:52","samples":3}}},"4022":{"weekday":{"815090":{"startSamples":[1079],"endSamples":[1080],"avgStart":"17:59","samples":1,"avgEnd":"18:00"},"815097":{"startSamples":[1007,1003],"endSamples":[1017,1013],"avgStart":"16:45","samples":2,"avgEnd":"16:55"}}},"4023":{"weekday":{"814999":{"startSamples":[1070,1065],"endSamples":[1080,1075],"avgStart":"17:48","samples":2,"avgEnd":"17:58"},"815033":{"startSamples":[1286],"endSamples":[1287],"avgStart":"21:26","samples":1,"avgEnd":"21:27"},"815109":{"startSamples":[1191,1185],"endSamples":[1293,1278],"avgStart":"19:48","samples":2,"avgEnd":"21:26"}}},"4024":{"weekday":{"814953":{"startSamples":[1140,1182],"endSamples":[1197,1192],"avgStart":"19:21","samples":2,"avgEnd":"19:55"},"815052":{"startSamples":[942],"endSamples":[945],"avgStart":"15:42","avgEnd":"15:45","samples":1},"815091":{"startSamples":[1122],"endSamples":[1123],"avgStart":"18:42","avgEnd":"18:43","samples":1},"815098":{"startSamples":[1007,1005],"endSamples":[1017,1013],"avgStart":"16:46","samples":2,"avgEnd":"16:55"}}},"4025":{"weekday":{"814954":{"startSamples":[1191,1190],"endSamples":[66,63],"avgStart":"19:51","samples":2,"avgEnd":"01:05"},"814995":{"startSamples":[1007,1003],"endSamples":[1017,1013],"avgStart":"16:45","samples":2,"avgEnd":"16:55"},"815014":{"startSamples":[1122],"endSamples":[1126],"avgStart":"18:42","avgEnd":"18:46","samples":1}}},"4026":{"weekday":{"815094":{"startSamples":[953,946],"endSamples":[963,952],"avgStart":"15:50","samples":2,"avgEnd":"15:58"},"815106":{"startSamples":[1135],"endSamples":[1142],"avgStart":"18:55","samples":1,"avgEnd":"19:02"}}},"4027":{"weekday":{"814937":{"startSamples":[53],"endSamples":[63],"avgStart":"00:53","samples":1,"avgEnd":"01:03"},"814939":{"startSamples":[1132,1122],"endSamples":[72,1132],"avgStart":"18:47","samples":2,"avgEnd":"10:02"},"815004":{"startSamples":[953,942],"endSamples":[963,952],"avgStart":"15:48","samples":2,"avgEnd":"15:58"}}},"4028":{"weekday":{"814940":{"startSamples":[1200],"endSamples":[1293],"avgStart":"20:00","samples":1,"avgEnd":"21:33"},"815102":{"startSamples":[1070,1065],"endSamples":[1195,1287],"avgStart":"17:48","samples":2,"avgEnd":"20:41"}}}}