{"route_short_name":"40","directions":{"0":"Eastbound","1":"Westbound"},"weekday":[{"trip_id":"794611","block_id":"9301","direction":0,"headsign":"2nd-Lombard","start":"05:05:00","end":"05:41:00","first":"52nd St & Heston St","last":"Lombard St & 2nd St - MBFS"},{"trip_id":"794610","block_id":"9303","direction":0,"headsign":"2nd-Lombard","start":"05:33:00","end":"06:10:00","first":"52nd St & Heston St","last":"Lombard St & 2nd St - MBFS"},{"trip_id":"794609","block_id":"9302","direction":0,"headsign":"2nd-Lombard","start":"05:39:00","end":"06:34:00","first":"Conshohocken Av & Monument Rd","last":"Lombard St & 2nd St - MBFS"},{"trip_id":"794684","block_id":"9301","direction":1,"headsign":"Conshohocken-Monument","start":"05:46:00","end":"06:48:00","first":"Lombard St & 2nd St - MBFS","last":"Conshohocken Av & Monument Rd"},{"trip_id":"794561","block_id":"9305","direction":0,"headsign":"2nd-Lombard","start":"05:54:00","end":"06:52:00","first":"Conshohocken Av & Monument Rd","last":"Lombard St & 2nd St - MBFS"},{"trip_id":"794690","block_id":"9304","direction":1,"headsign":"Conshohocken-Monument","start":"06:00:00","end":"07:07:00","first":"Lombard St & 2nd St - MBFS","last":"Conshohocken Av & Monument Rd"},{"trip_id":"794608","block_id":"9307","direction":0,"headsign":"2nd-Lombard","start":"06:05:00","end":"07:05:00","first":"Conshohocken Av & Monument Rd","last":"Lombard St & 2nd St - MBFS"},{"trip_id":"794751","block_id":"9306","direction":1,"headsign":"50th-Parkside","start":"06:11:00","end":"06:57:00","first":"Lombard St & 2nd St - MBFS","last":"50th & Parkside Loop"},{"trip_id":"794605","block_id":"9308","direction":0,"headsign":"2nd-Lombard","start":"06:12:00","end":"07:14:00","first":"Conshohocken Av & Monument Rd","last":"Lombard St & 2nd St - MBFS"},{"trip_id":"794683","block_id":"9303","direction":1,"headsign":"Conshohocken-Monument","start":"06:21:00","end":"07:30:00","first":"Lombard St & 2nd St - MBFS","last":"Conshohocken Av & Monument Rd"},{"trip_id":"794669","block_id":"9310","direction":0,"headsign":"2nd-Lombard","start":"06:28:00","end":"07:30:00","first":"Conshohocken Av & Monument Rd","last":"Lombard St & 2nd St - MBFS"},{"trip_id":"794749","block_id":"9309","direction":1,"headsign":"50th-Parkside","start":"06:35:00","end":"07:23:00","first":"Lombard St & 2nd St - MBFS","last":"50th & Parkside Loop"},{"trip_id":"794586","block_id":"9311","direction":0,"headsign":"2nd-Lombard","start":"06:37:00","end":"07:22:00","first":"50th & Parkside Loop","last":"Lombard St & 2nd St - MBFS"},{"trip_id":"794604","block_id":"9312","direction":0,"headsign":"2nd-Lombard","start":"06:43:00","end":"07:47:00","first":"Conshohocken Av & Monument Rd","last":"Lombard St & 2nd St - MBFS"},{"trip_id":"794696","block_id":"9302","direction":1,"headsign":"Conshohocken-Monument","start":"06:48:00","end":"07:58:00","first":"Lombard St & 2nd St - MBFS","last":"Conshohocken Av & Monument Rd"},{"trip_id":"794579","block_id":"9313","direction":0,"headsign":"2nd-Lombard","start":"06:53:00","end":"07:38:00","first":"50th & Parkside Loop","last":"Lombard St & 2nd St - MBFS"},{"trip_id":"794602","block_id":"9301","direction":0,"headsign":"2nd-Lombard","start":"06:56:00","end":"08:04:00","first":"Conshohocken Av & Monument Rd","last":"Lombard St & 2nd St - MBFS"},{"trip_id":"794747","block_id":"9305","direction":1,"headsign":"50th-Parkside","start":"07:00:00","end":"07:49:00","first":"Lombard St & 2nd St - MBFS","last":"50th & Parkside Loop"},{"trip_id":"794588","block_id":"9306","direction":0,"headsign":"2nd-Lombard","start":"07:09:00","end":"07:55:00","first":"50th & Parkside Loop","last":"Lombard St & 2nd St - MBFS"},{"trip_id":"794691","block_id":"9307","direction":1,"headsign":"Conshohocken-Monument","start":"07:11:00","end":"08:23:00","first":"Lombard St & 2nd St - MBFS","last":"Conshohocken Av & Monument Rd"},{"trip_id":"794745","block_id":"9314","direction":1,"headsign":"50th-Parkside","start":"07:20:00","end":"08:11:00","first":"Lombard St & 2nd St - MBFS","last":"50th & Parkside Loop"},{"trip_id":"794591","block_id":"9304","direction":0,"headsign":"2nd-Lombard","start":"07:21:00","end":"08:31:00","first":"Conshohocken Av & Monument Rd","last":"Lombard St & 2nd St - MBFS"},{"trip_id":"794743","block_id":"9308","direction":1,"headsign":"Conshohocken-Monument","start":"07:27:00","end":"08:40:00","first":"Lombard St & 2nd St - MBFS","last":"Conshohocken Av & Monument Rd"},{"trip_id":"794589","block_id":"9309","direction":0,"headsign":"2nd-Lombard","start":"07:28:00","end":"08:17:00","first":"50th & Parkside Loop","last":"Lombard St & 2nd St - MBFS"},{"trip_id":"794746","block_id":"9311","direction":1,"headsign":"50th-Parkside","start":"07:34:00","end":"08:25:00","first":"Lombard St & 2nd St - MBFS","last":"50th & Parkside Loop"},{"trip_id":"794695","block_id":"9310","direction":1,"headsign":"50th-Parkside","start":"07:41:00","end":"08:32:00","first":"Lombard St & 2nd St - MBFS","last":"50th & Parkside Loop"},{"trip_id":"794590","block_id":"9303","direction":0,"headsign":"2nd-Lombard","start":"07:47:00","end":"08:57:00","first":"Conshohocken Av & Monument Rd","last":"Lombard St & 2nd St - MBFS"},{"trip_id":"794692","block_id":"9313","direction":1,"headsign":"Conshohocken-Monument","start":"07:48:00","end":"09:01:00","first":"Lombard St & 2nd St - MBFS","last":"Conshohocken Av & Monument Rd"},{"trip_id":"794623","block_id":"9305","direction":0,"headsign":"2nd-Lombard","start":"07:55:00","end":"08:45:00","first":"50th & Parkside Loop","last":"Lombard St & 2nd St - MBFS"},{"trip_id":"794744","block_id":"9312","direction":1,"headsign":"Conshohocken-Monument","start":"07:55:00","end":"09:08:00","first":"Lombard St & 2nd St - MBFS","last":"Conshohocken Av & Monument Rd"},{"trip_id":"794694","block_id":"9306","direction":1,"headsign":"50th-Parkside","start":"08:02:00","end":"08:53:00","first":"Lombard St & 2nd St - MBFS","last":"50th & Parkside Loop"},{"trip_id":"794742","block_id":"9301","direction":1,"headsign":"Conshohocken-Monument","start":"08:09:00","end":"09:21:00","first":"Lombard St & 2nd St - MBFS","last":"Conshohocken Av & Monument Rd"},{"trip_id":"794587","block_id":"9302","direction":0,"headsign":"2nd-Lombard","start":"08:11:00","end":"09:21:00","first":"Conshohocken Av & Monument Rd","last":"Lombard St & 2nd St - MBFS"},{"trip_id":"794737","block_id":"9255","direction":1,"headsign":"50th-Parkside","start":"08:16:00","end":"09:07:00","first":"Lombard St & 2nd St - MBFS","last":"50th & Parkside Loop"},{"trip_id":"794668","block_id":"9314","direction":0,"headsign":"2nd-Lombard","start":"08:19:00","end":"09:09:00","first":"50th & Parkside Loop","last":"Lombard St & 2nd St - MBFS"},{"trip_id":"794750","block_id":"9505","direction":1,"headsign":"50th-Parkside","start":"08:23:00","end":"09:14:00","first":"Lombard St & 2nd St - MBFS","last":"50th & Parkside Loop"},{"trip_id":"794740","block_id":"9309","direction":1,"headsign":"Conshohocken-Monument","start":"08:30:00","end":"09:41:00","first":"Lombard St & 2nd St - MBFS","last":"Conshohocken Av & Monument Rd"},{"trip_id":"794585","block_id":"9307","direction":0,"headsign":"2nd-Lombard","start":"08:40:00","end":"09:51:00","first":"Conshohocken Av & Monument Rd","last":"Lombard St & 2nd St - MBFS"},{"trip_id":"794738","block_id":"9304","direction":1,"headsign":"Conshohocken-Monument","start":"08:41:00","end":"09:51:00","first":"Lombard St & 2nd St - MBFS","last":"Conshohocken Av & Monument Rd"},{"trip_id":"794584","block_id":"9310","direction":0,"headsign":"2nd-Lombard","start":"08:45:00","end":"09:36:00","first":"50th & Parkside Loop","last":"Lombard St & 2nd St - MBFS"},{"trip_id":"794739","block_id":"9305","direction":1,"headsign":"Conshohocken-Monument","start":"08:51:00","end":"10:01:00","first":"Lombard St & 2nd St - MBFS","last":"Conshohocken Av & Monument Rd"},{"trip_id":"794583","block_id":"9308","direction":0,"headsign":"2nd-Lombard","start":"08:56:00","end":"10:06:00","first":"Conshohocken Av & Monument Rd","last":"Lombard St & 2nd St - MBFS"},{"trip_id":"794732","block_id":"9303","direction":1,"headsign":"Conshohocken-Monument","start":"09:03:00","end":"10:13:00","first":"Lombard St & 2nd St - MBFS","last":"Conshohocken Av & Monument Rd"},{"trip_id":"794578","block_id":"9313","direction":0,"headsign":"2nd-Lombard","start":"09:11:00","end":"10:21:00","first":"Conshohocken Av & Monument Rd","last":"Lombard St & 2nd St - MBFS"},{"trip_id":"794735","block_id":"9314","direction":1,"headsign":"Conshohocken-Monument","start":"09:15:00","end":"10:26:00","first":"Lombard St & 2nd St - MBFS","last":"Conshohocken Av & Monument Rd"},{"trip_id":"794560","block_id":"9312","direction":0,"headsign":"2nd-Lombard","start":"09:26:00","end":"10:36:00","first":"Conshohocken Av & Monument Rd","last":"Lombard St & 2nd St - MBFS"},{"trip_id":"794753","block_id":"9302","direction":1,"headsign":"Conshohocken-Monument","start":"09:27:00","end":"10:38:00","first":"Lombard St & 2nd St - MBFS","last":"Conshohocken Av & Monument Rd"},{"trip_id":"794567","block_id":"9315","direction":0,"headsign":"2nd-Lombard","start":"09:41:00","end":"10:51:00","first":"Conshohocken Av & Monument Rd","last":"Lombard St & 2nd St - MBFS"},{"trip_id":"794731","block_id":"9310","direction":1,"headsign":"Conshohocken-Monument","start":"09:42:00","end":"10:52:00","first":"Lombard St & 2nd St - MBFS","last":"Conshohocken Av & Monument Rd"},{"trip_id":"794568","block_id":"9309","direction":0,"headsign":"2nd-Lombard","start":"09:57:00","end":"11:06:00","first":"Conshohocken Av & Monument Rd","last":"Lombard St & 2nd St - MBFS"},{"trip_id":"794730","block_id":"9307","direction":1,"headsign":"Conshohocken-Monument","start":"09:59:00","end":"11:07:00","first":"Lombard St & 2nd St - MBFS","last":"Conshohocken Av & Monument Rd"},{"trip_id":"794581","block_id":"9304","direction":0,"headsign":"2nd-Lombard","start":"10:12:00","end":"11:22:00","first":"Conshohocken Av & Monument Rd","last":"Lombard St & 2nd St - MBFS"},{"trip_id":"794729","block_id":"9308","direction":1,"headsign":"Conshohocken-Monument","start":"10:14:00","end":"11:22:00","first":"Lombard St & 2nd St - MBFS","last":"Conshohocken Av & Monument Rd"},{"trip_id":"794565","block_id":"9305","direction":0,"headsign":"2nd-Lombard","start":"10:27:00","end":"11:37:00","first":"Conshohocken Av & Monument Rd","last":"Lombard St & 2nd St - MBFS"},{"trip_id":"794728","block_id":"9313","direction":1,"headsign":"Conshohocken-Monument","start":"10:29:00","end":"11:38:00","first":"Lombard St & 2nd St - MBFS","last":"Conshohocken Av & Monument Rd"},{"trip_id":"794667","block_id":"9314","direction":0,"headsign":"2nd-Lombard","start":"10:41:00","end":"11:51:00","first":"Conshohocken Av & Monument Rd","last":"Lombard St & 2nd St - MBFS"},{"trip_id":"794727","block_id":"9312","direction":1,"headsign":"Conshohocken-Monument","start":"10:44:00","end":"11:53:00","first":"Lombard St & 2nd St - MBFS","last":"Conshohocken Av & Monument Rd"},{"trip_id":"794564","block_id":"9302","direction":0,"headsign":"2nd-Lombard","start":"10:56:00","end":"12:06:00","first":"Conshohocken Av & Monument Rd","last":"Lombard St & 2nd St - MBFS"},{"trip_id":"794688","block_id":"9315","direction":1,"headsign":"Conshohocken-Monument","start":"10:59:00","end":"12:08:00","first":"Lombard St & 2nd St - MBFS","last":"Conshohocken Av & Monument Rd"},{"trip_id":"794562","block_id":"9310","direction":0,"headsign":"2nd-Lombard","start":"11:11:00","end":"12:21:00","first":"Conshohocken Av & Monument Rd","last":"Lombard St & 2nd St - MBFS"},{"trip_id":"794726","block_id":"9309","direction":1,"headsign":"Conshohocken-Monument","start":"11:14:00","end":"12:23:00","first":"Lombard St & 2nd St - MBFS","last":"Conshohocken Av & Monument Rd"},{"trip_id":"794577","block_id":"9514","direction":0,"headsign":"2nd-Lombard","start":"11:26:00","end":"12:37:00","first":"Conshohocken Av & Monument Rd","last":"Lombard St & 2nd St - MBFS"},{"trip_id":"794733","block_id":"9304","direction":1,"headsign":"Conshohocken-Monument","start":"11:29:00","end":"12:38:00","first":"Lombard St & 2nd St - MBFS","last":"Conshohocken Av & Monument Rd"},{"trip_id":"794576","block_id":"9308","direction":0,"headsign":"2nd-Lombard","start":"11:42:00","end":"12:53:00","first":"Conshohocken Av & Monument Rd","last":"Lombard St & 2nd St - MBFS"},{"trip_id":"794687","block_id":"9305","direction":1,"headsign":"Conshohocken-Monument","start":"11:44:00","end":"12:53:00","first":"Lombard St & 2nd St - MBFS","last":"Conshohocken Av & Monument Rd"},{"trip_id":"794563","block_id":"9313","direction":0,"headsign":"2nd-Lombard","start":"11:57:00","end":"13:08:00","first":"Conshohocken Av & Monument Rd","last":"Lombard St & 2nd St - MBFS"},{"trip_id":"794752","block_id":"9314","direction":1,"headsign":"Conshohocken-Monument","start":"11:59:00","end":"13:08:00","first":"Lombard St & 2nd St - MBFS","last":"Conshohocken Av & Monument Rd"},{"trip_id":"794575","block_id":"9312","direction":0,"headsign":"2nd-Lombard","start":"12:12:00","end":"13:24:00","first":"Conshohocken Av & Monument Rd","last":"Lombard St & 2nd St - MBFS"},{"trip_id":"794741","block_id":"9302","direction":1,"headsign":"Conshohocken-Monument","start":"12:14:00","end":"13:23:00","first":"Lombard St & 2nd St - MBFS","last":"Conshohocken Av & Monument Rd"},{"trip_id":"794574","block_id":"9316","direction":0,"headsign":"2nd-Lombard","start":"12:27:00","end":"13:39:00","first":"Conshohocken Av & Monument Rd","last":"Lombard St & 2nd St - MBFS"},{"trip_id":"794716","block_id":"9310","direction":1,"headsign":"Conshohocken-Monument","start":"12:29:00","end":"13:38:00","first":"Lombard St & 2nd St - MBFS","last":"Conshohocken Av & Monument Rd"},{"trip_id":"794612","block_id":"9317","direction":0,"headsign":"2nd-Lombard","start":"12:42:00","end":"13:54:00","first":"Conshohocken Av & Monument Rd","last":"Lombard St & 2nd St - MBFS"},{"trip_id":"794712","block_id":"9514","direction":1,"headsign":"Conshohocken-Monument","start":"12:44:00","end":"13:53:00","first":"Lombard St & 2nd St - MBFS","last":"Conshohocken Av & Monument Rd"},{"trip_id":"794573","block_id":"9304","direction":0,"headsign":"2nd-Lombard","start":"12:57:00","end":"14:09:00","first":"Conshohocken Av & Monument Rd","last":"Lombard St & 2nd St - MBFS"},{"trip_id":"794715","block_id":"9308","direction":1,"headsign":"Conshohocken-Monument","start":"12:59:00","end":"14:08:00","first":"Lombard St & 2nd St - MBFS","last":"Conshohocken Av & Monument Rd"},{"trip_id":"794572","block_id":"9305","direction":0,"headsign":"2nd-Lombard","start":"13:10:00","end":"14:22:00","first":"Conshohocken Av & Monument Rd","last":"Lombard St & 2nd St - MBFS"},{"trip_id":"794636","block_id":"9305","direction":0,"headsign":"2nd-Lombard via Pine St","start":"13:10:00","end":"14:23:00","first":"Conshohocken Av & Monument Rd","last":"Lombard St & 2nd St - MBFS"},{"trip_id":"794686","block_id":"9313","direction":1,"headsign":"Conshohocken-Monument","start":"13:14:00","end":"14:23:00","first":"Lombard St & 2nd St - MBFS","last":"Conshohocken Av & Monument Rd"},{"trip_id":"794570","block_id":"9318","direction":0,"headsign":"2nd-Lombard","start":"13:23:00","end":"14:36:00","first":"Conshohocken Av & Monument Rd","last":"Lombard St & 2nd St - MBFS"},{"trip_id":"794634","block_id":"9318","direction":0,"headsign":"2nd-Lombard via Pine St","start":"13:23:00","end":"14:37:00","first":"Conshohocken Av & Monument Rd","last":"Lombard St & 2nd St - MBFS"},{"trip_id":"794714","block_id":"9312","direction":1,"headsign":"Conshohocken-Monument","start":"13:29:00","end":"14:38:00","first":"Lombard St & 2nd St - MBFS","last":"Conshohocken Av & Monument Rd"},{"trip_id":"794601","block_id":"9319","direction":0,"headsign":"2nd-Lombard","start":"13:35:00","end":"14:50:00","first":"Conshohocken Av & Monument Rd","last":"Lombard St & 2nd St - MBFS"},{"trip_id":"794648","block_id":"9319","direction":0,"headsign":"2nd-Lombard via Pine St","start":"13:35:00","end":"14:51:00","first":"Conshohocken Av & Monument Rd","last":"Lombard St & 2nd St - MBFS"},{"trip_id":"794713","block_id":"9316","direction":1,"headsign":"Conshohocken-Monument","start":"13:44:00","end":"14:53:00","first":"Lombard St & 2nd St - MBFS","last":"Conshohocken Av & Monument Rd"},{"trip_id":"794622","block_id":"9302","direction":0,"headsign":"2nd-Lombard","start":"13:47:00","end":"15:02:00","first":"Conshohocken Av & Monument Rd","last":"Lombard St & 2nd St - MBFS"},{"trip_id":"794661","block_id":"9302","direction":0,"headsign":"2nd-Lombard via Pine St","start":"13:47:00","end":"15:03:00","first":"Conshohocken Av & Monument Rd","last":"Lombard St & 2nd St - MBFS"},{"trip_id":"794621","block_id":"9320","direction":0,"headsign":"2nd-Lombard","start":"13:58:00","end":"15:14:00","first":"Conshohocken Av & Monument Rd","last":"Lombard St & 2nd St - MBFS"},{"trip_id":"794660","block_id":"9320","direction":0,"headsign":"2nd-Lombard via Pine St","start":"13:58:00","end":"15:15:00","first":"Conshohocken Av & Monument Rd","last":"Lombard St & 2nd St - MBFS"},{"trip_id":"794689","block_id":"9317","direction":1,"headsign":"Conshohocken-Monument","start":"13:59:00","end":"15:08:00","first":"Lombard St & 2nd St - MBFS","last":"Conshohocken Av & Monument Rd"},{"trip_id":"794620","block_id":"9514","direction":0,"headsign":"2nd-Lombard","start":"14:10:00","end":"15:27:00","first":"Conshohocken Av & Monument Rd","last":"Lombard St & 2nd St - MBFS"},{"trip_id":"794659","block_id":"9514","direction":0,"headsign":"2nd-Lombard via Pine St","start":"14:10:00","end":"15:28:00","first":"Conshohocken Av & Monument Rd","last":"Lombard St & 2nd St - MBFS"},{"trip_id":"794711","block_id":"9304","direction":1,"headsign":"Conshohocken-Monument","start":"14:14:00","end":"15:26:00","first":"Lombard St & 2nd St - MBFS","last":"Conshohocken Av & Monument Rd"},{"trip_id":"794619","block_id":"9321","direction":0,"headsign":"2nd-Lombard","start":"14:22:00","end":"15:40:00","first":"Conshohocken Av & Monument Rd","last":"Lombard St & 2nd St - MBFS"},{"trip_id":"794658","block_id":"9321","direction":0,"headsign":"2nd-Lombard via Pine St","start":"14:22:00","end":"15:41:00","first":"Conshohocken Av & Monument Rd","last":"Lombard St & 2nd St - MBFS"},{"trip_id":"794709","block_id":"9661","direction":1,"headsign":"50th-Parkside","start":"14:26:00","end":"15:13:00","first":"Lombard St & 2nd St - MBFS","last":"50th & Parkside Loop"},{"trip_id":"794558","block_id":"9322","direction":0,"headsign":"2nd-Lombard","start":"14:34:00","end":"15:52:00","first":"Conshohocken Av & Monument Rd","last":"Lombard St & 2nd St - MBFS"},{"trip_id":"794630","block_id":"9322","direction":0,"headsign":"2nd-Lombard via Pine St","start":"14:34:00","end":"15:53:00","first":"Conshohocken Av & Monument Rd","last":"Lombard St & 2nd St - MBFS"},{"trip_id":"794710","block_id":"9305","direction":1,"headsign":"Conshohocken-Monument","start":"14:35:00","end":"15:49:00","first":"Lombard St & 2nd St - MBFS","last":"Conshohocken Av & Monument Rd"},{"trip_id":"794569","block_id":"9323","direction":0,"headsign":"2nd-Lombard","start":"14:44:00","end":"16:03:00","first":"Conshohocken Av & Monument Rd","last":"Lombard St & 2nd St - MBFS"},{"trip_id":"794633","block_id":"9323","direction":0,"headsign":"2nd-Lombard via Pine St","start":"14:44:00","end":"16:04:00","first":"Conshohocken Av & Monument Rd","last":"Lombard St & 2nd St - MBFS"},{"trip_id":"794685","block_id":"9318","direction":1,"headsign":"50th-Parkside","start":"14:46:00","end":"15:36:00","first":"Lombard St & 2nd St - MBFS","last":"50th & Parkside Loop"},{"trip_id":"794734","block_id":"9319","direction":1,"headsign":"Conshohocken-Monument","start":"14:58:00","end":"16:13:00","first":"Lombard St & 2nd St - MBFS","last":"Conshohocken Av & Monument Rd"},{"trip_id":"794566","block_id":"9316","direction":0,"headsign":"2nd-Lombard","start":"15:04:00","end":"16:23:00","first":"Conshohocken Av & Monument Rd","last":"Lombard St & 2nd St - MBFS"},{"trip_id":"794632","block_id":"9316","direction":0,"headsign":"2nd-Lombard via Pine St","start":"15:04:00","end":"16:24:00","first":"Conshohocken Av & Monument Rd","last":"Lombard St & 2nd St - MBFS"},{"trip_id":"794708","block_id":"9302","direction":1,"headsign":"50th-Parkside","start":"15:10:00","end":"16:00:00","first":"Lombard St & 2nd St - MBFS","last":"50th & Parkside Loop"},{"trip_id":"794557","block_id":"9324","direction":0,"headsign":"2nd-Lombard","start":"15:14:00","end":"16:13:00","first":"50th & Parkside Loop","last":"Lombard St & 2nd St - MBFS"},{"trip_id":"794629","block_id":"9324","direction":0,"headsign":"2nd-Lombard via Pine St","start":"15:14:00","end":"16:14:00","first":"50th & Parkside Loop","last":"Lombard St & 2nd St - MBFS"},{"trip_id":"794706","block_id":"9320","direction":1,"headsign":"Conshohocken-Monument","start":"15:22:00","end":"16:37:00","first":"Lombard St & 2nd St - MBFS","last":"Conshohocken Av & Monument Rd"},{"trip_id":"794571","block_id":"9317","direction":0,"headsign":"2nd-Lombard","start":"15:24:00","end":"16:43:00","first":"Conshohocken Av & Monument Rd","last":"Lombard St & 2nd St - MBFS"},{"trip_id":"794635","block_id":"9317","direction":0,"headsign":"2nd-Lombard via Pine St","start":"15:24:00","end":"16:44:00","first":"Conshohocken Av & Monument Rd","last":"Lombard St & 2nd St - MBFS"},{"trip_id":"794600","block_id":"9661","direction":0,"headsign":"2nd-Lombard","start":"15:34:00","end":"16:33:00","first":"50th & Parkside Loop","last":"Lombard St & 2nd St - MBFS"},{"trip_id":"794647","block_id":"9661","direction":0,"headsign":"2nd-Lombard via Pine St","start":"15:34:00","end":"16:34:00","first":"50th & Parkside Loop","last":"Lombard St & 2nd St - MBFS"},{"trip_id":"794682","block_id":"9514","direction":1,"headsign":"Conshohocken-Monument","start":"15:35:00","end":"16:50:00","first":"Lombard St & 2nd St - MBFS","last":"Conshohocken Av & Monument Rd"},{"trip_id":"794582","block_id":"9304","direction":0,"headsign":"2nd-Lombard","start":"15:44:00","end":"17:03:00","first":"Conshohocken Av & Monument Rd","last":"Lombard St & 2nd St - MBFS"},{"trip_id":"794638","block_id":"9304","direction":0,"headsign":"2nd-Lombard via Pine St","start":"15:44:00","end":"17:04:00","first":"Conshohocken Av & Monument Rd","last":"Lombard St & 2nd St - MBFS"},{"trip_id":"794707","block_id":"9321","direction":1,"headsign":"50th-Parkside","start":"15:47:00","end":"16:37:00","first":"Lombard St & 2nd St - MBFS","last":"50th & Parkside Loop"},{"trip_id":"794580","block_id":"9318","direction":0,"headsign":"2nd-Lombard","start":"15:54:00","end":"16:53:00","first":"50th & Parkside Loop","last":"Lombard St & 2nd St - MBFS"},{"trip_id":"794637","block_id":"9318","direction":0,"headsign":"2nd-Lombard via Pine St","start":"15:54:00","end":"16:54:00","first":"50th & Parkside Loop","last":"Lombard St & 2nd St - MBFS"},{"trip_id":"794705","block_id":"9322","direction":1,"headsign":"Conshohocken-Monument","start":"15:59:00","end":"17:14:00","first":"Lombard St & 2nd St - MBFS","last":"Conshohocken Av & Monument Rd"},{"trip_id":"794598","block_id":"9325","direction":0,"headsign":"2nd-Lombard","start":"16:04:00","end":"17:23:00","first":"Conshohocken Av & Monument Rd","last":"Lombard St & 2nd St - MBFS"},{"trip_id":"794645","block_id":"9325","direction":0,"headsign":"2nd-Lombard via Pine St","start":"16:04:00","end":"17:24:00","first":"Conshohocken Av & Monument Rd","last":"Lombard St & 2nd St - MBFS"},{"trip_id":"794674","block_id":"9323","direction":1,"headsign":"50th-Parkside","start":"16:09:00","end":"16:59:00","first":"Lombard St & 2nd St - MBFS","last":"50th & Parkside Loop"},{"trip_id":"794597","block_id":"9302","direction":0,"headsign":"2nd-Lombard","start":"16:14:00","end":"17:13:00","first":"50th & Parkside Loop","last":"Lombard St & 2nd St - MBFS"},{"trip_id":"794644","block_id":"9302","direction":0,"headsign":"2nd-Lombard via Pine St","start":"16:14:00","end":"17:14:00","first":"50th & Parkside Loop","last":"Lombard St & 2nd St - MBFS"},{"trip_id":"794672","block_id":"9324","direction":1,"headsign":"Conshohocken-Monument","start":"16:19:00","end":"17:33:00","first":"Lombard St & 2nd St - MBFS","last":"Conshohocken Av & Monument Rd"},{"trip_id":"794559","block_id":"9319","direction":0,"headsign":"2nd-Lombard","start":"16:24:00","end":"17:43:00","first":"Conshohocken Av & Monument Rd","last":"Lombard St & 2nd St - MBFS"},{"trip_id":"794631","block_id":"9319","direction":0,"headsign":"2nd-Lombard via Pine St","start":"16:24:00","end":"17:44:00","first":"Conshohocken Av & Monument Rd","last":"Lombard St & 2nd St - MBFS"},{"trip_id":"794704","block_id":"9316","direction":1,"headsign":"50th-Parkside","start":"16:30:00","end":"17:18:00","first":"Lombard St & 2nd St - MBFS","last":"50th & Parkside Loop"},{"trip_id":"794599","block_id":"9326","direction":0,"headsign":"2nd-Lombard","start":"16:34:00","end":"17:33:00","first":"50th & Parkside Loop","last":"Lombard St & 2nd St - MBFS"},{"trip_id":"794646","block_id":"9326","direction":0,"headsign":"2nd-Lombard via Pine St","start":"16:34:00","end":"17:34:00","first":"50th & Parkside Loop","last":"Lombard St & 2nd St - MBFS"},{"trip_id":"794703","block_id":"9661","direction":1,"headsign":"Conshohocken-Monument","start":"16:41:00","end":"17:52:00","first":"Lombard St & 2nd St - MBFS","last":"Conshohocken Av & Monument Rd"},{"trip_id":"794595","block_id":"9320","direction":0,"headsign":"2nd-Lombard","start":"16:46:00","end":"18:03:00","first":"Conshohocken Av & Monument Rd","last":"Lombard St & 2nd St - MBFS"},{"trip_id":"794642","block_id":"9320","direction":0,"headsign":"2nd-Lombard via Pine St","start":"16:46:00","end":"18:04:00","first":"Conshohocken Av & Monument Rd","last":"Lombard St & 2nd St - MBFS"},{"trip_id":"794700","block_id":"9317","direction":1,"headsign":"50th-Parkside","start":"16:51:00","end":"17:38:00","first":"Lombard St & 2nd St - MBFS","last":"50th & Parkside Loop"},{"trip_id":"794596","block_id":"9321","direction":0,"headsign":"2nd-Lombard","start":"16:55:00","end":"17:53:00","first":"50th & Parkside Loop","last":"Lombard St & 2nd St - MBFS"},{"trip_id":"794643","block_id":"9321","direction":0,"headsign":"2nd-Lombard via Pine St","start":"16:55:00","end":"17:54:00","first":"50th & Parkside Loop","last":"Lombard St & 2nd St - MBFS"},{"trip_id":"794702","block_id":"9318","direction":1,"headsign":"Conshohocken-Monument","start":"16:59:00","end":"18:10:00","first":"Lombard St & 2nd St - MBFS","last":"Conshohocken Av & Monument Rd"},{"trip_id":"794593","block_id":"9514","direction":0,"headsign":"2nd-Lombard","start":"17:07:00","end":"18:23:00","first":"Conshohocken Av & Monument Rd","last":"Lombard St & 2nd St - MBFS"},{"trip_id":"794640","block_id":"9514","direction":0,"headsign":"2nd-Lombard via Pine St","start":"17:07:00","end":"18:24:00","first":"Conshohocken Av & Monument Rd","last":"Lombard St & 2nd St - MBFS"},{"trip_id":"794701","block_id":"9304","direction":1,"headsign":"50th-Parkside","start":"17:09:00","end":"17:56:00","first":"Lombard St & 2nd St - MBFS","last":"50th & Parkside Loop"},{"trip_id":"794594","block_id":"9323","direction":0,"headsign":"2nd-Lombard","start":"17:15:00","end":"18:12:00","first":"50th & Parkside Loop","last":"Lombard St & 2nd St - MBFS"},{"trip_id":"794641","block_id":"9323","direction":0,"headsign":"2nd-Lombard via Pine St","start":"17:15:00","end":"18:13:00","first":"50th & Parkside Loop","last":"Lombard St & 2nd St - MBFS"},{"trip_id":"794699","block_id":"9302","direction":1,"headsign":"Conshohocken-Monument","start":"17:19:00","end":"18:27:00","first":"Lombard St & 2nd St - MBFS","last":"Conshohocken Av & Monument Rd"},{"trip_id":"794670","block_id":"9322","direction":0,"headsign":"2nd-Lombard","start":"17:21:00","end":"18:35:00","first":"Conshohocken Av & Monument Rd","last":"Lombard St & 2nd St - MBFS"},{"trip_id":"794671","block_id":"9322","direction":0,"headsign":"2nd-Lombard via Pine St","start":"17:21:00","end":"18:36:00","first":"Conshohocken Av & Monument Rd","last":"Lombard St & 2nd St - MBFS"},{"trip_id":"794736","block_id":"9325","direction":1,"headsign":"Conshohocken-Monument","start":"17:30:00","end":"18:36:00","first":"Lombard St & 2nd St - MBFS","last":"Conshohocken Av & Monument Rd"},{"trip_id":"794592","block_id":"9327","direction":0,"headsign":"2nd-Lombard","start":"17:39:00","end":"18:50:00","first":"Conshohocken Av & Monument Rd","last":"Lombard St & 2nd St - MBFS"},{"trip_id":"794639","block_id":"9327","direction":0,"headsign":"2nd-Lombard via Pine St","start":"17:39:00","end":"18:51:00","first":"Conshohocken Av & Monument Rd","last":"Lombard St & 2nd St - MBFS"},{"trip_id":"794693","block_id":"9326","direction":1,"headsign":"50th-Parkside","start":"17:40:00","end":"18:24:00","first":"Lombard St & 2nd St - MBFS","last":"50th & Parkside Loop"},{"trip_id":"794673","block_id":"9319","direction":1,"headsign":"Conshohocken-Monument","start":"17:50:00","end":"18:56:00","first":"Lombard St & 2nd St - MBFS","last":"Conshohocken Av & Monument Rd"},{"trip_id":"794627","block_id":"9324","direction":0,"headsign":"2nd-Lombard","start":"18:00:00","end":"19:10:00","first":"Conshohocken Av & Monument Rd","last":"Lombard St & 2nd St - MBFS"},{"trip_id":"794665","block_id":"9324","direction":0,"headsign":"2nd-Lombard via Pine St","start":"18:00:00","end":"19:11:00","first":"Conshohocken Av & Monument Rd","last":"Lombard St & 2nd St - MBFS"},{"trip_id":"794698","block_id":"9321","direction":1,"headsign":"50th-Parkside","start":"18:00:00","end":"18:44:00","first":"Lombard St & 2nd St - MBFS","last":"50th & Parkside Loop"},{"trip_id":"794697","block_id":"9320","direction":1,"headsign":"Conshohocken-Monument","start":"18:10:00","end":"19:15:00","first":"Lombard St & 2nd St - MBFS","last":"Conshohocken Av & Monument Rd"},{"trip_id":"794626","block_id":"9661","direction":0,"headsign":"2nd-Lombard","start":"18:20:00","end":"19:29:00","first":"Conshohocken Av & Monument Rd","last":"Lombard St & 2nd St - MBFS"},{"trip_id":"794664","block_id":"9661","direction":0,"headsign":"2nd-Lombard via Pine St","start":"18:20:00","end":"19:30:00","first":"Conshohocken Av & Monument Rd","last":"Lombard St & 2nd St - MBFS"},{"trip_id":"794681","block_id":"9323","direction":1,"headsign":"Conshohocken-Monument","start":"18:21:00","end":"19:25:00","first":"Lombard St & 2nd St - MBFS","last":"Conshohocken Av & Monument Rd"},{"trip_id":"794680","block_id":"9514","direction":1,"headsign":"Conshohocken-Monument","start":"18:32:00","end":"19:36:00","first":"Lombard St & 2nd St - MBFS","last":"Conshohocken Av & Monument Rd"},{"trip_id":"794625","block_id":"9325","direction":0,"headsign":"2nd-Lombard","start":"18:44:00","end":"19:52:00","first":"Conshohocken Av & Monument Rd","last":"Lombard St & 2nd St - MBFS"},{"trip_id":"794663","block_id":"9325","direction":0,"headsign":"2nd-Lombard via Pine St","start":"18:44:00","end":"19:53:00","first":"Conshohocken Av & Monument Rd","last":"Lombard St & 2nd St - MBFS"},{"trip_id":"794754","block_id":"9322","direction":1,"headsign":"Conshohocken-Monument","start":"18:44:00","end":"19:47:00","first":"Lombard St & 2nd St - MBFS","last":"Conshohocken Av & Monument Rd"},{"trip_id":"794679","block_id":"9327","direction":1,"headsign":"Conshohocken-Monument","start":"19:00:00","end":"20:02:00","first":"Lombard St & 2nd St - MBFS","last":"Conshohocken Av & Monument Rd"},{"trip_id":"794624","block_id":"9326","direction":0,"headsign":"2nd-Lombard","start":"19:10:00","end":"20:16:00","first":"Conshohocken Av & Monument Rd","last":"Lombard St & 2nd St - MBFS"},{"trip_id":"794662","block_id":"9326","direction":0,"headsign":"2nd-Lombard via Pine St","start":"19:10:00","end":"20:17:00","first":"Conshohocken Av & Monument Rd","last":"Lombard St & 2nd St - MBFS"},{"trip_id":"794678","block_id":"9324","direction":1,"headsign":"Conshohocken-Monument","start":"19:17:00","end":"20:19:00","first":"Lombard St & 2nd St - MBFS","last":"Conshohocken Av & Monument Rd"},{"trip_id":"794677","block_id":"9661","direction":1,"headsign":"Conshohocken-Monument","start":"19:38:00","end":"20:39:00","first":"Lombard St & 2nd St - MBFS","last":"Conshohocken Av & Monument Rd"},{"trip_id":"794628","block_id":"9323","direction":0,"headsign":"2nd-Lombard","start":"19:40:00","end":"20:43:00","first":"Conshohocken Av & Monument Rd","last":"Lombard St & 2nd St - MBFS"},{"trip_id":"794666","block_id":"9323","direction":0,"headsign":"2nd-Lombard via Pine St","start":"19:40:00","end":"20:44:00","first":"Conshohocken Av & Monument Rd","last":"Lombard St & 2nd St - MBFS"},{"trip_id":"794676","block_id":"9325","direction":1,"headsign":"Conshohocken-Monument","start":"20:00:00","end":"20:59:00","first":"Lombard St & 2nd St - MBFS","last":"Conshohocken Av & Monument Rd"},{"trip_id":"794607","block_id":"9327","direction":0,"headsign":"2nd-Lombard","start":"20:10:00","end":"21:12:00","first":"Conshohocken Av & Monument Rd","last":"Lombard St & 2nd St - MBFS"},{"trip_id":"794651","block_id":"9327","direction":0,"headsign":"2nd-Lombard via Pine St","start":"20:10:00","end":"21:13:00","first":"Conshohocken Av & Monument Rd","last":"Lombard St & 2nd St - MBFS"},{"trip_id":"794675","block_id":"9326","direction":1,"headsign":"Conshohocken-Monument","start":"20:23:00","end":"21:22:00","first":"Lombard St & 2nd St - MBFS","last":"Conshohocken Av & Monument Rd"},{"trip_id":"794606","block_id":"9324","direction":0,"headsign":"2nd-Lombard","start":"20:42:00","end":"21:40:00","first":"Conshohocken Av & Monument Rd","last":"Lombard St & 2nd St - MBFS"},{"trip_id":"794650","block_id":"9324","direction":0,"headsign":"2nd-Lombard via Pine St","start":"20:42:00","end":"21:41:00","first":"Conshohocken Av & Monument Rd","last":"Lombard St & 2nd St - MBFS"},{"trip_id":"794748","block_id":"9323","direction":1,"headsign":"Conshohocken-Monument","start":"20:49:00","end":"21:47:00","first":"Lombard St & 2nd St - MBFS","last":"Conshohocken Av & Monument Rd"},{"trip_id":"794603","block_id":"9325","direction":0,"headsign":"2nd-Lombard","start":"21:12:00","end":"22:09:00","first":"Conshohocken Av & Monument Rd","last":"Lombard St & 2nd St - MBFS"},{"trip_id":"794649","block_id":"9325","direction":0,"headsign":"2nd-Lombard via Pine St","start":"21:12:00","end":"22:10:00","first":"Conshohocken Av & Monument Rd","last":"Lombard St & 2nd St - MBFS"},{"trip_id":"794725","block_id":"9327","direction":1,"headsign":"Conshohocken-Monument","start":"21:18:00","end":"22:16:00","first":"Lombard St & 2nd St - MBFS","last":"Conshohocken Av & Monument Rd"},{"trip_id":"794618","block_id":"9326","direction":0,"headsign":"2nd-Lombard","start":"21:42:00","end":"22:37:00","first":"Conshohocken Av & Monument Rd","last":"Lombard St & 2nd St - MBFS"},{"trip_id":"794657","block_id":"9326","direction":0,"headsign":"2nd-Lombard via Pine St","start":"21:42:00","end":"22:38:00","first":"Conshohocken Av & Monument Rd","last":"Lombard St & 2nd St - MBFS"},{"trip_id":"794724","block_id":"9324","direction":1,"headsign":"Conshohocken-Monument","start":"21:46:00","end":"22:44:00","first":"Lombard St & 2nd St - MBFS","last":"Conshohocken Av & Monument Rd"},{"trip_id":"794723","block_id":"9325","direction":1,"headsign":"Conshohocken-Monument","start":"22:16:00","end":"23:14:00","first":"Lombard St & 2nd St - MBFS","last":"Conshohocken Av & Monument Rd"},{"trip_id":"794617","block_id":"9323","direction":0,"headsign":"2nd-Lombard","start":"22:18:00","end":"23:12:00","first":"Conshohocken Av & Monument Rd","last":"Lombard St & 2nd St - MBFS"},{"trip_id":"794656","block_id":"9323","direction":0,"headsign":"2nd-Lombard via Pine St","start":"22:18:00","end":"23:13:00","first":"Conshohocken Av & Monument Rd","last":"Lombard St & 2nd St - MBFS"},{"trip_id":"794722","block_id":"9326","direction":1,"headsign":"Conshohocken-Monument","start":"22:46:00","end":"23:44:00","first":"Lombard St & 2nd St - MBFS","last":"Conshohocken Av & Monument Rd"},{"trip_id":"794616","block_id":"9327","direction":0,"headsign":"2nd-Lombard","start":"22:53:00","end":"23:47:00","first":"Conshohocken Av & Monument Rd","last":"Lombard St & 2nd St - MBFS"},{"trip_id":"794655","block_id":"9327","direction":0,"headsign":"2nd-Lombard via Pine St","start":"22:53:00","end":"23:48:00","first":"Conshohocken Av & Monument Rd","last":"Lombard St & 2nd St - MBFS"},{"trip_id":"794721","block_id":"9323","direction":1,"headsign":"Conshohocken-Monument","start":"23:19:00","end":"24:16:00","first":"Lombard St & 2nd St - MBFS","last":"Conshohocken Av & Monument Rd"},{"trip_id":"794615","block_id":"9325","direction":0,"headsign":"2nd-Lombard","start":"23:29:00","end":"24:19:00","first":"Conshohocken Av & Monument Rd","last":"Lombard St & 2nd St - MBFS"},{"trip_id":"794654","block_id":"9325","direction":0,"headsign":"2nd-Lombard via Pine St","start":"23:29:00","end":"24:20:00","first":"Conshohocken Av & Monument Rd","last":"Lombard St & 2nd St - MBFS"},{"trip_id":"794720","block_id":"9327","direction":1,"headsign":"Conshohocken-Monument","start":"23:54:00","end":"24:46:00","first":"Lombard St & 2nd St - MBFS","last":"Conshohocken Av & Monument Rd"},{"trip_id":"794614","block_id":"9326","direction":0,"headsign":"2nd-Lombard","start":"24:12:00","end":"24:58:00","first":"Conshohocken Av & Monument Rd","last":"Lombard St & 2nd St - MBFS"},{"trip_id":"794653","block_id":"9326","direction":0,"headsign":"2nd-Lombard via Pine St","start":"24:12:00","end":"24:59:00","first":"Conshohocken Av & Monument Rd","last":"Lombard St & 2nd St - MBFS"},{"trip_id":"794719","block_id":"9325","direction":1,"headsign":"Conshohocken-Monument","start":"24:26:00","end":"25:18:00","first":"Lombard St & 2nd St - MBFS","last":"Conshohocken Av & Monument Rd"},{"trip_id":"794613","block_id":"9327","direction":0,"headsign":"2nd-Lombard","start":"24:57:00","end":"25:43:00","first":"Conshohocken Av & Monument Rd","last":"Lombard St & 2nd St - MBFS"},{"trip_id":"794652","block_id":"9327","direction":0,"headsign":"2nd-Lombard via Pine St","start":"24:57:00","end":"25:44:00","first":"Conshohocken Av & Monument Rd","last":"Lombard St & 2nd St - MBFS"},{"trip_id":"794718","block_id":"9326","direction":1,"headsign":"Conshohocken-Monument","start":"25:04:00","end":"25:56:00","first":"Lombard St & 2nd St - MBFS","last":"Conshohocken Av & Monument Rd"},{"trip_id":"794717","block_id":"9327","direction":1,"headsign":"Conshohocken-Monument","start":"25:49:00","end":"26:41:00","first":"Lombard St & 2nd St - MBFS","last":"Conshohocken Av & Monument Rd"}],"saturday":[{"trip_id":"794957","block_id":"9301","direction":0,"headsign":"2nd-Lombard","start":"05:07:00","end":"05:41:00","first":"52nd St & Heston St","last":"Lombard St & 2nd St - MBFS"},{"trip_id":"794958","block_id":"9302","direction":0,"headsign":"2nd-Lombard","start":"05:38:00","end":"06:26:00","first":"Conshohocken Av & Monument Rd","last":"Lombard St & 2nd St - MBFS"},{"trip_id":"795000","block_id":"9301","direction":1,"headsign":"Conshohocken-Monument","start":"05:47:00","end":"06:40:00","first":"Lombard St & 2nd St - MBFS","last":"Conshohocken Av & Monument Rd"},{"trip_id":"794959","block_id":"9303","direction":0,"headsign":"2nd-Lombard","start":"06:18:00","end":"07:08:00","first":"Conshohocken Av & Monument Rd","last":"Lombard St & 2nd St - MBFS"},{"trip_id":"795001","block_id":"9302","direction":1,"headsign":"Conshohocken-Monument","start":"06:31:00","end":"07:26:00","first":"Lombard St & 2nd St - MBFS","last":"Conshohocken Av & Monument Rd"},{"trip_id":"794960","block_id":"9301","direction":0,"headsign":"2nd-Lombard","start":"06:53:00","end":"07:47:00","first":"Conshohocken Av & Monument Rd","last":"Lombard St & 2nd St - MBFS"},{"trip_id":"795002","block_id":"9303","direction":1,"headsign":"Conshohocken-Monument","start":"07:16:00","end":"08:12:00","first":"Lombard St & 2nd St - MBFS","last":"Conshohocken Av & Monument Rd"},{"trip_id":"794948","block_id":"9304","direction":0,"headsign":"2nd-Lombard","start":"07:23:00","end":"08:18:00","first":"Conshohocken Av & Monument Rd","last":"Lombard St & 2nd St - MBFS"},{"trip_id":"794961","block_id":"9302","direction":0,"headsign":"2nd-Lombard","start":"07:53:00","end":"08:50:00","first":"Conshohocken Av & Monument Rd","last":"Lombard St & 2nd St - MBFS"},{"trip_id":"795006","block_id":"9301","direction":1,"headsign":"Conshohocken-Monument","start":"07:54:00","end":"08:53:00","first":"Lombard St & 2nd St - MBFS","last":"Conshohocken Av & Monument Rd"},{"trip_id":"794962","block_id":"9303","direction":0,"headsign":"2nd-Lombard","start":"08:21:00","end":"09:18:00","first":"Conshohocken Av & Monument Rd","last":"Lombard St & 2nd St - MBFS"},{"trip_id":"794987","block_id":"9304","direction":1,"headsign":"Conshohocken-Monument","start":"08:26:00","end":"09:26:00","first":"Lombard St & 2nd St - MBFS","last":"Conshohocken Av & Monument Rd"},{"trip_id":"794963","block_id":"9305","direction":0,"headsign":"2nd-Lombard","start":"08:48:00","end":"09:46:00","first":"Conshohocken Av & Monument Rd","last":"Lombard St & 2nd St - MBFS"},{"trip_id":"795007","block_id":"9302","direction":1,"headsign":"Conshohocken-Monument","start":"08:57:00","end":"09:57:00","first":"Lombard St & 2nd St - MBFS","last":"Conshohocken Av & Monument Rd"},{"trip_id":"794964","block_id":"9301","direction":0,"headsign":"2nd-Lombard","start":"09:15:00","end":"10:14:00","first":"Conshohocken Av & Monument Rd","last":"Lombard St & 2nd St - MBFS"},{"trip_id":"795008","block_id":"9303","direction":1,"headsign":"Conshohocken-Monument","start":"09:27:00","end":"10:28:00","first":"Lombard St & 2nd St - MBFS","last":"Conshohocken Av & Monument Rd"},{"trip_id":"794965","block_id":"9304","direction":0,"headsign":"2nd-Lombard","start":"09:41:00","end":"10:44:00","first":"Conshohocken Av & Monument Rd","last":"Lombard St & 2nd St - MBFS"},{"trip_id":"795009","block_id":"9305","direction":1,"headsign":"Conshohocken-Monument","start":"09:57:00","end":"10:59:00","first":"Lombard St & 2nd St - MBFS","last":"Conshohocken Av & Monument Rd"},{"trip_id":"794966","block_id":"9302","direction":0,"headsign":"2nd-Lombard","start":"10:09:00","end":"11:13:00","first":"Conshohocken Av & Monument Rd","last":"Lombard St & 2nd St - MBFS"},{"trip_id":"795010","block_id":"9301","direction":1,"headsign":"Conshohocken-Monument","start":"10:25:00","end":"11:27:00","first":"Lombard St & 2nd St - MBFS","last":"Conshohocken Av & Monument Rd"},{"trip_id":"794967","block_id":"9306","direction":0,"headsign":"2nd-Lombard","start":"10:37:00","end":"11:42:00","first":"Conshohocken Av & Monument Rd","last":"Lombard St & 2nd St - MBFS"},{"trip_id":"795011","block_id":"9304","direction":1,"headsign":"Conshohocken-Monument","start":"10:53:00","end":"11:55:00","first":"Lombard St & 2nd St - MBFS","last":"Conshohocken Av & Monument Rd"},{"trip_id":"794969","block_id":"9402","direction":0,"headsign":"2nd-Lombard","start":"11:04:00","end":"12:11:00","first":"Conshohocken Av & Monument Rd","last":"Lombard St & 2nd St - MBFS"},{"trip_id":"795003","block_id":"9302","direction":1,"headsign":"Conshohocken-Monument","start":"11:20:00","end":"12:23:00","first":"Lombard St & 2nd St - MBFS","last":"Conshohocken Av & Monument Rd"},{"trip_id":"794968","block_id":"9305","direction":0,"headsign":"2nd-Lombard","start":"11:30:00","end":"12:37:00","first":"Conshohocken Av & Monument Rd","last":"Lombard St & 2nd St - MBFS"},{"trip_id":"795004","block_id":"9306","direction":1,"headsign":"Conshohocken-Monument","start":"11:48:00","end":"12:53:00","first":"Lombard St & 2nd St - MBFS","last":"Conshohocken Av & Monument Rd"},{"trip_id":"794947","block_id":"9301","direction":0,"headsign":"2nd-Lombard via Pine St","start":"12:00:00","end":"13:08:00","first":"Conshohocken Av & Monument Rd","last":"Lombard St & 2nd St - MBFS"},{"trip_id":"795012","block_id":"9402","direction":1,"headsign":"Conshohocken-Monument","start":"12:17:00","end":"13:23:00","first":"Lombard St & 2nd St - MBFS","last":"Conshohocken Av & Monument Rd"},{"trip_id":"794970","block_id":"9304","direction":0,"headsign":"2nd-Lombard via Pine St","start":"12:30:00","end":"13:39:00","first":"Conshohocken Av & Monument Rd","last":"Lombard St & 2nd St - MBFS"},{"trip_id":"795005","block_id":"9305","direction":1,"headsign":"Conshohocken-Monument","start":"12:47:00","end":"13:52:00","first":"Lombard St & 2nd St - MBFS","last":"Conshohocken Av & Monument Rd"},{"trip_id":"794971","block_id":"9302","direction":0,"headsign":"2nd-Lombard via Pine St","start":"13:00:00","end":"14:09:00","first":"Conshohocken Av & Monument Rd","last":"Lombard St & 2nd St - MBFS"},{"trip_id":"794986","block_id":"9301","direction":1,"headsign":"Conshohocken-Monument","start":"13:16:00","end":"14:22:00","first":"Lombard St & 2nd St - MBFS","last":"Conshohocken Av & Monument Rd"},{"trip_id":"794972","block_id":"9307","direction":0,"headsign":"2nd-Lombard via Pine St","start":"13:30:00","end":"14:39:00","first":"Conshohocken Av & Monument Rd","last":"Lombard St & 2nd St - MBFS"},{"trip_id":"795013","block_id":"9304","direction":1,"headsign":"Conshohocken-Monument","start":"13:46:00","end":"14:52:00","first":"Lombard St & 2nd St - MBFS","last":"Conshohocken Av & Monument Rd"},{"trip_id":"794973","block_id":"9305","direction":0,"headsign":"2nd-Lombard via Pine St","start":"14:00:00","end":"15:09:00","first":"Conshohocken Av & Monument Rd","last":"Lombard St & 2nd St - MBFS"},{"trip_id":"795014","block_id":"9302","direction":1,"headsign":"Conshohocken-Monument","start":"14:16:00","end":"15:22:00","first":"Lombard St & 2nd St - MBFS","last":"Conshohocken Av & Monument Rd"},{"trip_id":"794974","block_id":"9308","direction":0,"headsign":"2nd-Lombard via Pine St","start":"14:30:00","end":"15:39:00","first":"Conshohocken Av & Monument Rd","last":"Lombard St & 2nd St - MBFS"},{"trip_id":"795015","block_id":"9307","direction":1,"headsign":"Conshohocken-Monument","start":"14:44:00","end":"15:50:00","first":"Lombard St & 2nd St - MBFS","last":"Conshohocken Av & Monument Rd"},{"trip_id":"794975","block_id":"9304","direction":0,"headsign":"2nd-Lombard via Pine St","start":"15:00:00","end":"16:09:00","first":"Conshohocken Av & Monument Rd","last":"Lombard St & 2nd St - MBFS"},{"trip_id":"795017","block_id":"9305","direction":1,"headsign":"Conshohocken-Monument","start":"15:15:00","end":"16:19:00","first":"Lombard St & 2nd St - MBFS","last":"Conshohocken Av & Monument Rd"},{"trip_id":"794976","block_id":"9309","direction":0,"headsign":"2nd-Lombard via Pine St","start":"15:30:00","end":"16:37:00","first":"Conshohocken Av & Monument Rd","last":"Lombard St & 2nd St - MBFS"},{"trip_id":"795016","block_id":"9308","direction":1,"headsign":"Conshohocken-Monument","start":"15:46:00","end":"16:49:00","first":"Lombard St & 2nd St - MBFS","last":"Conshohocken Av & Monument Rd"},{"trip_id":"794977","block_id":"9307","direction":0,"headsign":"2nd-Lombard via Pine St","start":"16:00:00","end":"17:07:00","first":"Conshohocken Av & Monument Rd","last":"Lombard St & 2nd St - MBFS"},{"trip_id":"795018","block_id":"9304","direction":1,"headsign":"Conshohocken-Monument","start":"16:16:00","end":"17:19:00","first":"Lombard St & 2nd St - MBFS","last":"Conshohocken Av & Monument Rd"},{"trip_id":"794978","block_id":"9305","direction":0,"headsign":"2nd-Lombard via Pine St","start":"16:31:00","end":"17:37:00","first":"Conshohocken Av & Monument Rd","last":"Lombard St & 2nd St - MBFS"},{"trip_id":"795019","block_id":"9309","direction":1,"headsign":"Conshohocken-Monument","start":"16:46:00","end":"17:48:00","first":"Lombard St & 2nd St - MBFS","last":"Conshohocken Av & Monument Rd"},{"trip_id":"794979","block_id":"9308","direction":0,"headsign":"2nd-Lombard via Pine St","start":"17:02:00","end":"18:07:00","first":"Conshohocken Av & Monument Rd","last":"Lombard St & 2nd St - MBFS"},{"trip_id":"795020","block_id":"9307","direction":1,"headsign":"Conshohocken-Monument","start":"17:16:00","end":"18:18:00","first":"Lombard St & 2nd St - MBFS","last":"Conshohocken Av & Monument Rd"},{"trip_id":"794980","block_id":"9310","direction":0,"headsign":"2nd-Lombard via Pine St","start":"17:32:00","end":"18:36:00","first":"Conshohocken Av & Monument Rd","last":"Lombard St & 2nd St - MBFS"},{"trip_id":"795021","block_id":"9305","direction":1,"headsign":"Conshohocken-Monument","start":"17:44:00","end":"18:45:00","first":"Lombard St & 2nd St - MBFS","last":"Conshohocken Av & Monument Rd"},{"trip_id":"794981","block_id":"9311","direction":0,"headsign":"2nd-Lombard via Pine St","start":"18:03:00","end":"19:06:00","first":"Conshohocken Av & Monument Rd","last":"Lombard St & 2nd St - MBFS"},{"trip_id":"795022","block_id":"9308","direction":1,"headsign":"Conshohocken-Monument","start":"18:12:00","end":"19:13:00","first":"Lombard St & 2nd St - MBFS","last":"Conshohocken Av & Monument Rd"},{"trip_id":"794982","block_id":"9309","direction":0,"headsign":"2nd-Lombard via Pine St","start":"18:33:00","end":"19:34:00","first":"Conshohocken Av & Monument Rd","last":"Lombard St & 2nd St - MBFS"},{"trip_id":"795023","block_id":"9310","direction":1,"headsign":"Conshohocken-Monument","start":"18:41:00","end":"19:41:00","first":"Lombard St & 2nd St - MBFS","last":"Conshohocken Av & Monument Rd"},{"trip_id":"794983","block_id":"9307","direction":0,"headsign":"2nd-Lombard via Pine St","start":"19:04:00","end":"20:04:00","first":"Conshohocken Av & Monument Rd","last":"Lombard St & 2nd St - MBFS"},{"trip_id":"795024","block_id":"9311","direction":1,"headsign":"Conshohocken-Monument","start":"19:11:00","end":"20:09:00","first":"Lombard St & 2nd St - MBFS","last":"Conshohocken Av & Monument Rd"},{"trip_id":"794984","block_id":"9308","direction":0,"headsign":"2nd-Lombard via Pine St","start":"19:34:00","end":"20:31:00","first":"Conshohocken Av & Monument Rd","last":"Lombard St & 2nd St - MBFS"},{"trip_id":"794988","block_id":"9309","direction":1,"headsign":"Conshohocken-Monument","start":"19:39:00","end":"20:35:00","first":"Lombard St & 2nd St - MBFS","last":"Conshohocken Av & Monument Rd"},{"trip_id":"794985","block_id":"9310","direction":0,"headsign":"2nd-Lombard via Pine St","start":"20:04:00","end":"21:01:00","first":"Conshohocken Av & Monument Rd","last":"Lombard St & 2nd St - MBFS"},{"trip_id":"794989","block_id":"9307","direction":1,"headsign":"Conshohocken-Monument","start":"20:09:00","end":"21:04:00","first":"Lombard St & 2nd St - MBFS","last":"Conshohocken Av & Monument Rd"},{"trip_id":"794949","block_id":"9311","direction":0,"headsign":"2nd-Lombard via Pine St","start":"20:37:00","end":"21:31:00","first":"Conshohocken Av & Monument Rd","last":"Lombard St & 2nd St - MBFS"},{"trip_id":"794990","block_id":"9308","direction":1,"headsign":"Conshohocken-Monument","start":"20:39:00","end":"21:34:00","first":"Lombard St & 2nd St - MBFS","last":"Conshohocken Av & Monument Rd"},{"trip_id":"794950","block_id":"9408","direction":0,"headsign":"2nd-Lombard via Pine St","start":"21:09:00","end":"22:03:00","first":"Conshohocken Av & Monument Rd","last":"Lombard St & 2nd St - MBFS"},{"trip_id":"794991","block_id":"9310","direction":1,"headsign":"Conshohocken-Monument","start":"21:10:00","end":"22:04:00","first":"Lombard St & 2nd St - MBFS","last":"Conshohocken Av & Monument Rd"},{"trip_id":"794992","block_id":"9311","direction":1,"headsign":"Conshohocken-Monument","start":"21:40:00","end":"22:33:00","first":"Lombard St & 2nd St - MBFS","last":"Conshohocken Av & Monument Rd"},{"trip_id":"794951","block_id":"9308","direction":0,"headsign":"2nd-Lombard via Pine St","start":"21:42:00","end":"22:35:00","first":"Conshohocken Av & Monument Rd","last":"Lombard St & 2nd St - MBFS"},{"trip_id":"794993","block_id":"9408","direction":1,"headsign":"Conshohocken-Monument","start":"22:11:00","end":"23:03:00","first":"Lombard St & 2nd St - MBFS","last":"Conshohocken Av & Monument Rd"},{"trip_id":"794952","block_id":"9310","direction":0,"headsign":"2nd-Lombard via Pine St","start":"22:16:00","end":"23:09:00","first":"Conshohocken Av & Monument Rd","last":"Lombard St & 2nd St - MBFS"},{"trip_id":"794994","block_id":"9308","direction":1,"headsign":"Conshohocken-Monument","start":"22:41:00","end":"23:34:00","first":"Lombard St & 2nd St - MBFS","last":"Conshohocken Av & Monument Rd"},{"trip_id":"794953","block_id":"9311","direction":0,"headsign":"2nd-Lombard via Pine St","start":"22:52:00","end":"23:44:00","first":"Conshohocken Av & Monument Rd","last":"Lombard St & 2nd St - MBFS"},{"trip_id":"794995","block_id":"9310","direction":1,"headsign":"Conshohocken-Monument","start":"23:14:00","end":"24:06:00","first":"Lombard St & 2nd St - MBFS","last":"Conshohocken Av & Monument Rd"},{"trip_id":"794954","block_id":"9408","direction":0,"headsign":"2nd-Lombard via Pine St","start":"23:29:00","end":"24:20:00","first":"Conshohocken Av & Monument Rd","last":"Lombard St & 2nd St - MBFS"},{"trip_id":"794996","block_id":"9311","direction":1,"headsign":"Conshohocken-Monument","start":"23:49:00","end":"24:41:00","first":"Lombard St & 2nd St - MBFS","last":"Conshohocken Av & Monument Rd"},{"trip_id":"794955","block_id":"9310","direction":0,"headsign":"2nd-Lombard via Pine St","start":"24:12:00","end":"24:59:00","first":"Conshohocken Av & Monument Rd","last":"Lombard St & 2nd St - MBFS"},{"trip_id":"794997","block_id":"9408","direction":1,"headsign":"Conshohocken-Monument","start":"24:26:00","end":"25:18:00","first":"Lombard St & 2nd St - MBFS","last":"Conshohocken Av & Monument Rd"},{"trip_id":"794956","block_id":"9311","direction":0,"headsign":"2nd-Lombard via Pine St","start":"24:57:00","end":"25:44:00","first":"Conshohocken Av & Monument Rd","last":"Lombard St & 2nd St - MBFS"},{"trip_id":"794998","block_id":"9310","direction":1,"headsign":"Conshohocken-Monument","start":"25:04:00","end":"25:56:00","first":"Lombard St & 2nd St - MBFS","last":"Conshohocken Av & Monument Rd"},{"trip_id":"794999","block_id":"9311","direction":1,"headsign":"Conshohocken-Monument","start":"25:49:00","end":"26:41:00","first":"Lombard St & 2nd St - MBFS","last":"Conshohocken Av & Monument Rd"}],"sunday":[{"trip_id":"795029","block_id":"9301","direction":0,"headsign":"2nd-Lombard","start":"05:10:00","end":"05:39:00","first":"52nd St & Heston St","last":"Lombard St & 2nd St - MBFS"},{"trip_id":"795028","block_id":"9302","direction":0,"headsign":"2nd-Lombard","start":"05:39:00","end":"06:26:00","first":"Conshohocken Av & Monument Rd","last":"Lombard St & 2nd St - MBFS"},{"trip_id":"795088","block_id":"9301","direction":1,"headsign":"Conshohocken-Monument","start":"05:50:00","end":"06:40:00","first":"Lombard St & 2nd St - MBFS","last":"Conshohocken Av & Monument Rd"},{"trip_id":"795027","block_id":"9902","direction":0,"headsign":"2nd-Lombard","start":"06:18:00","end":"07:06:00","first":"Conshohocken Av & Monument Rd","last":"Lombard St & 2nd St - MBFS"},{"trip_id":"795087","block_id":"9302","direction":1,"headsign":"Conshohocken-Monument","start":"06:31:00","end":"07:24:00","first":"Lombard St & 2nd St - MBFS","last":"Conshohocken Av & Monument Rd"},{"trip_id":"795031","block_id":"9301","direction":0,"headsign":"2nd-Lombard","start":"06:56:00","end":"07:46:00","first":"Conshohocken Av & Monument Rd","last":"Lombard St & 2nd St - MBFS"},{"trip_id":"795063","block_id":"9902","direction":1,"headsign":"Conshohocken-Monument","start":"07:11:00","end":"08:05:00","first":"Lombard St & 2nd St - MBFS","last":"Conshohocken Av & Monument Rd"},{"trip_id":"795026","block_id":"9302","direction":0,"headsign":"2nd-Lombard","start":"07:32:00","end":"08:22:00","first":"Conshohocken Av & Monument Rd","last":"Lombard St & 2nd St - MBFS"},{"trip_id":"795086","block_id":"9301","direction":1,"headsign":"Conshohocken-Monument","start":"07:51:00","end":"08:46:00","first":"Lombard St & 2nd St - MBFS","last":"Conshohocken Av & Monument Rd"},{"trip_id":"795025","block_id":"9303","direction":0,"headsign":"2nd-Lombard","start":"08:00:00","end":"08:52:00","first":"Conshohocken Av & Monument Rd","last":"Lombard St & 2nd St - MBFS"},{"trip_id":"795085","block_id":"9302","direction":1,"headsign":"Conshohocken-Monument","start":"08:27:00","end":"09:24:00","first":"Lombard St & 2nd St - MBFS","last":"Conshohocken Av & Monument Rd"},{"trip_id":"795062","block_id":"9304","direction":0,"headsign":"2nd-Lombard","start":"08:30:00","end":"09:23:00","first":"Conshohocken Av & Monument Rd","last":"Lombard St & 2nd St - MBFS"},{"trip_id":"795061","block_id":"9301","direction":0,"headsign":"2nd-Lombard","start":"09:00:00","end":"09:53:00","first":"Conshohocken Av & Monument Rd","last":"Lombard St & 2nd St - MBFS"},{"trip_id":"795084","block_id":"9303","direction":1,"headsign":"Conshohocken-Monument","start":"09:00:00","end":"09:57:00","first":"Lombard St & 2nd St - MBFS","last":"Conshohocken Av & Monument Rd"},{"trip_id":"795060","block_id":"9305","direction":0,"headsign":"2nd-Lombard","start":"09:30:00","end":"10:27:00","first":"Conshohocken Av & Monument Rd","last":"Lombard St & 2nd St - MBFS"},{"trip_id":"795083","block_id":"9304","direction":1,"headsign":"Conshohocken-Monument","start":"09:32:00","end":"10:29:00","first":"Lombard St & 2nd St - MBFS","last":"Conshohocken Av & Monument Rd"},{"trip_id":"795059","block_id":"9302","direction":0,"headsign":"2nd-Lombard","start":"09:58:00","end":"10:55:00","first":"Conshohocken Av & Monument Rd","last":"Lombard St & 2nd St - MBFS"},{"trip_id":"795082","block_id":"9301","direction":1,"headsign":"Conshohocken-Monument","start":"10:02:00","end":"11:01:00","first":"Lombard St & 2nd St - MBFS","last":"Conshohocken Av & Monument Rd"},{"trip_id":"795058","block_id":"9303","direction":0,"headsign":"2nd-Lombard","start":"10:26:00","end":"11:23:00","first":"Conshohocken Av & Monument Rd","last":"Lombard St & 2nd St - MBFS"},{"trip_id":"795081","block_id":"9305","direction":1,"headsign":"Conshohocken-Monument","start":"10:32:00","end":"11:31:00","first":"Lombard St & 2nd St - MBFS","last":"Conshohocken Av & Monument Rd"},{"trip_id":"795057","block_id":"9304","direction":0,"headsign":"2nd-Lombard","start":"10:54:00","end":"11:51:00","first":"Conshohocken Av & Monument Rd","last":"Lombard St & 2nd St - MBFS"},{"trip_id":"795080","block_id":"9302","direction":1,"headsign":"Conshohocken-Monument","start":"11:02:00","end":"12:01:00","first":"Lombard St & 2nd St - MBFS","last":"Conshohocken Av & Monument Rd"},{"trip_id":"795030","block_id":"9301","direction":0,"headsign":"2nd-Lombard","start":"11:22:00","end":"12:19:00","first":"Conshohocken Av & Monument Rd","last":"Lombard St & 2nd St - MBFS"},{"trip_id":"795079","block_id":"9303","direction":1,"headsign":"Conshohocken-Monument","start":"11:30:00","end":"12:29:00","first":"Lombard St & 2nd St - MBFS","last":"Conshohocken Av & Monument Rd"},{"trip_id":"795056","block_id":"9305","direction":0,"headsign":"2nd-Lombard via Pine St","start":"11:48:00","end":"12:50:00","first":"Conshohocken Av & Monument Rd","last":"Lombard St & 2nd St - MBFS"},{"trip_id":"795078","block_id":"9304","direction":1,"headsign":"Conshohocken-Monument","start":"11:58:00","end":"12:59:00","first":"Lombard St & 2nd St - MBFS","last":"Conshohocken Av & Monument Rd"},{"trip_id":"795055","block_id":"9302","direction":0,"headsign":"2nd-Lombard via Pine St","start":"12:18:00","end":"13:20:00","first":"Conshohocken Av & Monument Rd","last":"Lombard St & 2nd St - MBFS"},{"trip_id":"795100","block_id":"9301","direction":1,"headsign":"Conshohocken-Monument","start":"12:28:00","end":"13:29:00","first":"Lombard St & 2nd St - MBFS","last":"Conshohocken Av & Monument Rd"},{"trip_id":"795054","block_id":"9508","direction":0,"headsign":"2nd-Lombard via Pine St","start":"12:48:00","end":"13:50:00","first":"Conshohocken Av & Monument Rd","last":"Lombard St & 2nd St - MBFS"},{"trip_id":"795077","block_id":"9305","direction":1,"headsign":"Conshohocken-Monument","start":"12:57:00","end":"13:59:00","first":"Lombard St & 2nd St - MBFS","last":"Conshohocken Av & Monument Rd"},{"trip_id":"795053","block_id":"9304","direction":0,"headsign":"2nd-Lombard via Pine St","start":"13:18:00","end":"14:19:00","first":"Conshohocken Av & Monument Rd","last":"Lombard St & 2nd St - MBFS"},{"trip_id":"795076","block_id":"9302","direction":1,"headsign":"Conshohocken-Monument","start":"13:27:00","end":"14:29:00","first":"Lombard St & 2nd St - MBFS","last":"Conshohocken Av & Monument Rd"},{"trip_id":"795052","block_id":"9452","direction":0,"headsign":"2nd-Lombard via Pine St","start":"13:48:00","end":"14:49:00","first":"Conshohocken Av & Monument Rd","last":"Lombard St & 2nd St - MBFS"},{"trip_id":"795075","block_id":"9508","direction":1,"headsign":"Conshohocken-Monument","start":"13:56:00","end":"14:59:00","first":"Lombard St & 2nd St - MBFS","last":"Conshohocken Av & Monument Rd"},{"trip_id":"795051","block_id":"9306","direction":0,"headsign":"2nd-Lombard via Pine St","start":"14:18:00","end":"15:19:00","first":"Conshohocken Av & Monument Rd","last":"Lombard St & 2nd St - MBFS"},{"trip_id":"795074","block_id":"9304","direction":1,"headsign":"Conshohocken-Monument","start":"14:26:00","end":"15:30:00","first":"Lombard St & 2nd St - MBFS","last":"Conshohocken Av & Monument Rd"},{"trip_id":"795050","block_id":"9305","direction":0,"headsign":"2nd-Lombard via Pine St","start":"14:48:00","end":"15:49:00","first":"Conshohocken Av & Monument Rd","last":"Lombard St & 2nd St - MBFS"},{"trip_id":"795073","block_id":"9452","direction":1,"headsign":"Conshohocken-Monument","start":"14:57:00","end":"16:00:00","first":"Lombard St & 2nd St - MBFS","last":"Conshohocken Av & Monument Rd"},{"trip_id":"795049","block_id":"9508","direction":0,"headsign":"2nd-Lombard via Pine St","start":"15:18:00","end":"16:18:00","first":"Conshohocken Av & Monument Rd","last":"Lombard St & 2nd St - MBFS"},{"trip_id":"795072","block_id":"9306","direction":1,"headsign":"Conshohocken-Monument","start":"15:27:00","end":"16:30:00","first":"Lombard St & 2nd St - MBFS","last":"Conshohocken Av & Monument Rd"},{"trip_id":"795048","block_id":"9304","direction":0,"headsign":"2nd-Lombard via Pine St","start":"15:48:00","end":"16:48:00","first":"Conshohocken Av & Monument Rd","last":"Lombard St & 2nd St - MBFS"},{"trip_id":"795071","block_id":"9305","direction":1,"headsign":"Conshohocken-Monument","start":"15:57:00","end":"17:00:00","first":"Lombard St & 2nd St - MBFS","last":"Conshohocken Av & Monument Rd"},{"trip_id":"795047","block_id":"9307","direction":0,"headsign":"2nd-Lombard via Pine St","start":"16:20:00","end":"17:20:00","first":"Conshohocken Av & Monument Rd","last":"Lombard St & 2nd St - MBFS"},{"trip_id":"795070","block_id":"9508","direction":1,"headsign":"Conshohocken-Monument","start":"16:27:00","end":"17:29:00","first":"Lombard St & 2nd St - MBFS","last":"Conshohocken Av & Monument Rd"},{"trip_id":"795046","block_id":"9306","direction":0,"headsign":"2nd-Lombard via Pine St","start":"16:52:00","end":"17:52:00","first":"Conshohocken Av & Monument Rd","last":"Lombard St & 2nd St - MBFS"},{"trip_id":"795069","block_id":"9304","direction":1,"headsign":"Conshohocken-Monument","start":"16:59:00","end":"17:59:00","first":"Lombard St & 2nd St - MBFS","last":"Conshohocken Av & Monument Rd"},{"trip_id":"795045","block_id":"9305","direction":0,"headsign":"2nd-Lombard via Pine St","start":"17:24:00","end":"18:22:00","first":"Conshohocken Av & Monument Rd","last":"Lombard St & 2nd St - MBFS"},{"trip_id":"795068","block_id":"9307","direction":1,"headsign":"Conshohocken-Monument","start":"17:29:00","end":"18:28:00","first":"Lombard St & 2nd St - MBFS","last":"Conshohocken Av & Monument Rd"},{"trip_id":"795044","block_id":"9308","direction":0,"headsign":"2nd-Lombard via Pine St","start":"17:57:00","end":"18:54:00","first":"Conshohocken Av & Monument Rd","last":"Lombard St & 2nd St - MBFS"},{"trip_id":"795067","block_id":"9306","direction":1,"headsign":"Conshohocken-Monument","start":"17:59:00","end":"18:58:00","first":"Lombard St & 2nd St - MBFS","last":"Conshohocken Av & Monument Rd"},{"trip_id":"795043","block_id":"9309","direction":0,"headsign":"2nd-Lombard via Pine St","start":"18:28:00","end":"19:24:00","first":"Conshohocken Av & Monument Rd","last":"Lombard St & 2nd St - MBFS"},{"trip_id":"795066","block_id":"9305","direction":1,"headsign":"Conshohocken-Monument","start":"18:29:00","end":"19:28:00","first":"Lombard St & 2nd St - MBFS","last":"Conshohocken Av & Monument Rd"},{"trip_id":"795042","block_id":"9307","direction":0,"headsign":"2nd-Lombard via Pine St","start":"19:00:00","end":"19:55:00","first":"Conshohocken Av & Monument Rd","last":"Lombard St & 2nd St - MBFS"},{"trip_id":"795065","block_id":"9308","direction":1,"headsign":"Conshohocken-Monument","start":"19:01:00","end":"19:58:00","first":"Lombard St & 2nd St - MBFS","last":"Conshohocken Av & Monument Rd"},{"trip_id":"795041","block_id":"9306","direction":0,"headsign":"2nd-Lombard via Pine St","start":"19:31:00","end":"20:26:00","first":"Conshohocken Av & Monument Rd","last":"Lombard St & 2nd St - MBFS"},{"trip_id":"795099","block_id":"9309","direction":1,"headsign":"Conshohocken-Monument","start":"19:31:00","end":"20:27:00","first":"Lombard St & 2nd St - MBFS","last":"Conshohocken Av & Monument Rd"},{"trip_id":"795098","block_id":"9307","direction":1,"headsign":"Conshohocken-Monument","start":"20:01:00","end":"20:57:00","first":"Lombard St & 2nd St - MBFS","last":"Conshohocken Av & Monument Rd"},{"trip_id":"795040","block_id":"9308","direction":0,"headsign":"2nd-Lombard via Pine St","start":"20:03:00","end":"20:57:00","first":"Conshohocken Av & Monument Rd","last":"Lombard St & 2nd St - MBFS"},{"trip_id":"795097","block_id":"9306","direction":1,"headsign":"Conshohocken-Monument","start":"20:31:00","end":"21:27:00","first":"Lombard St & 2nd St - MBFS","last":"Conshohocken Av & Monument Rd"},{"trip_id":"795039","block_id":"9309","direction":0,"headsign":"2nd-Lombard via Pine St","start":"20:35:00","end":"21:27:00","first":"Conshohocken Av & Monument Rd","last":"Lombard St & 2nd St - MBFS"},{"trip_id":"795096","block_id":"9308","direction":1,"headsign":"Conshohocken-Monument","start":"21:02:00","end":"21:57:00","first":"Lombard St & 2nd St - MBFS","last":"Conshohocken Av & Monument Rd"},{"trip_id":"795038","block_id":"9307","direction":0,"headsign":"2nd-Lombard via Pine St","start":"21:09:00","end":"22:00:00","first":"Conshohocken Av & Monument Rd","last":"Lombard St & 2nd St - MBFS"},{"trip_id":"795095","block_id":"9309","direction":1,"headsign":"Conshohocken-Monument","start":"21:32:00","end":"22:27:00","first":"Lombard St & 2nd St - MBFS","last":"Conshohocken Av & Monument Rd"},{"trip_id":"795037","block_id":"9306","direction":0,"headsign":"2nd-Lombard via Pine St","start":"21:43:00","end":"22:34:00","first":"Conshohocken Av & Monument Rd","last":"Lombard St & 2nd St - MBFS"},{"trip_id":"795064","block_id":"9307","direction":1,"headsign":"Conshohocken-Monument","start":"22:05:00","end":"22:59:00","first":"Lombard St & 2nd St - MBFS","last":"Conshohocken Av & Monument Rd"},{"trip_id":"795036","block_id":"9308","direction":0,"headsign":"2nd-Lombard via Pine St","start":"22:18:00","end":"23:09:00","first":"Conshohocken Av & Monument Rd","last":"Lombard St & 2nd St - MBFS"},{"trip_id":"795094","block_id":"9306","direction":1,"headsign":"Conshohocken-Monument","start":"22:39:00","end":"23:33:00","first":"Lombard St & 2nd St - MBFS","last":"Conshohocken Av & Monument Rd"},{"trip_id":"795035","block_id":"9309","direction":0,"headsign":"2nd-Lombard via Pine St","start":"22:55:00","end":"23:43:00","first":"Conshohocken Av & Monument Rd","last":"Lombard St & 2nd St - MBFS"},{"trip_id":"795093","block_id":"9308","direction":1,"headsign":"Conshohocken-Monument","start":"23:14:00","end":"24:07:00","first":"Lombard St & 2nd St - MBFS","last":"Conshohocken Av & Monument Rd"},{"trip_id":"795034","block_id":"9307","direction":0,"headsign":"2nd-Lombard via Pine St","start":"23:32:00","end":"24:18:00","first":"Conshohocken Av & Monument Rd","last":"Lombard St & 2nd St - MBFS"},{"trip_id":"795092","block_id":"9309","direction":1,"headsign":"Conshohocken-Monument","start":"23:50:00","end":"24:42:00","first":"Lombard St & 2nd St - MBFS","last":"Conshohocken Av & Monument Rd"},{"trip_id":"795033","block_id":"9308","direction":0,"headsign":"2nd-Lombard via Pine St","start":"24:12:00","end":"24:58:00","first":"Conshohocken Av & Monument Rd","last":"Lombard St & 2nd St - MBFS"},{"trip_id":"795091","block_id":"9307","direction":1,"headsign":"Conshohocken-Monument","start":"24:26:00","end":"25:18:00","first":"Lombard St & 2nd St - MBFS","last":"Conshohocken Av & Monument Rd"},{"trip_id":"795032","block_id":"9309","direction":0,"headsign":"2nd-Lombard via Pine St","start":"24:57:00","end":"25:43:00","first":"Conshohocken Av & Monument Rd","last":"Lombard St & 2nd St - MBFS"},{"trip_id":"795090","block_id":"9308","direction":1,"headsign":"Conshohocken-Monument","start":"25:04:00","end":"25:56:00","first":"Lombard St & 2nd St - MBFS","last":"Conshohocken Av & Monument Rd"},{"trip_id":"795089","block_id":"9309","direction":1,"headsign":"Conshohocken-Monument","start":"25:49:00","end":"26:41:00","first":"Lombard St & 2nd St - MBFS","last":"Conshohocken Av & Monument Rd"}]}